<?xml version="1.0" encoding="utf-8"?>
<presentation width="960" height="540" isRTL="0" preview="0" enableAccessibility="NaN" defaultSlideDuration="5" start="play" slideTitleFormat="%n. %s" buildNum="11.0.0.133">
	<presentationTitle>Chapitre 1 : Titre du cours</presentationTitle>
	<speakers>
		<speaker>
			<name>Joel LUNARDI</name>
			<speakerTitle>Professeur de Biochimie (Université Joseph Fourier - Grenoble)</speakerTitle>
			<image>spk10037.jpg</image>
		</speaker>
		<speaker>
			<name>Julien FAURÉ</name>
			<speakerTitle>Maitre de conference-CHU de Grenoble</speakerTitle>
			<image>spk13724.jpg</image>
		</speaker>
		<speaker>
			<name>Jean-Paul STAHL</name>
			<speakerTitle>CHU de Grenoble</speakerTitle>
			<image>spk14447.jpg</image>
		</speaker>
		<speaker>
			<name>Prénom NOM</name>
			<speakerTitle>Enseignant de la Faculté</speakerTitle>
			<image>spk130656.jpg</image>
		</speaker>
		<speaker>
			<name>Denis Wouessi djewe</name>
			<speakerTitle>Professeur CHU Grenoble (UGA)</speakerTitle>
			<image>spk131566.jpg</image>
		</speaker>
	</speakers>
	<search url="srchdata.xml"/>
	<presentationBg url="bg.swf"/>
	<masters><master url="Master0.swf" id="1" totalFrames="1"><backdrop frameNum="0"/><slidexml><AS3Class className="TL_d8994d8bb49d401aac5376ad6766edc8yxy" classType="PptTmline_xyxyxyxyxyxyxyxyxyxyxyxyxyxy" frameRate="30"><OnLoadCallBacks/><Audios/></AS3Class></slidexml></master><master url="Master1.swf" id="2" totalFrames="1"><backdrop frameNum="1"/><slidexml><AS3Class className="TL_b1555bd5c4be440194d3cd6e58d1f325yxy" classType="PptTmline_xyxyxyxyxyxyxyxyxyxyxyxyxyxy" frameRate="30"><OnLoadCallBacks/><Audios/></AS3Class></slidexml></master></masters>
	<layouts><layout url="Layout0.swf" id="1" totalFrames="1"><backdrop displayBgSp="true"/><slidexml><AS3Class className="TL_91d45ea5b51c48bdb10d1c26bbd33a40yxy" classType="PptTmline_xyxyxyxyxyxyxyxyxyxyxyxyxyxy" frameRate="30"><OnLoadCallBacks/><Audios/></AS3Class></slidexml></layout><layout url="Layout1.swf" id="2" totalFrames="1"><backdrop displayBgSp="true"/><slidexml><AS3Class className="TL_459246fedcb441e8a20cf82516fdd0c5yxy" classType="PptTmline_xyxyxyxyxyxyxyxyxyxyxyxyxyxy" frameRate="30"><OnLoadCallBacks/><Audios/></AS3Class></slidexml></layout><layout url="Layout2.swf" id="3" totalFrames="1"><backdrop displayBgSp="true"/><slidexml><AS3Class className="TL_39c9c2b1b5794b04b4fbc8188319a59cyxy" classType="PptTmline_xyxyxyxyxyxyxyxyxyxyxyxyxyxy" frameRate="30"><OnLoadCallBacks/><Audios/></AS3Class></slidexml></layout></layouts>
	<slides>
		<slide id="413" showInTOC="" inSequence="" frameRate="30" totalFrames="30" usePptxSlideDur="0" lockInteractionSlide="false" isHiddenInteractionSl="false" isWrongInteractionSl="false" swfConvertorEngine="Nova" slideDuration="8.93" advance="auto" blockMovement="false" hideplaybar="false" type="normal">
			<content url="Slide0.swf" id="413"/>
			<backdrop displayBgSp="true"/>
			<master id="1" frameNum="0"/>
			<layout id="1" frameNum="0"/>
			<slidexml><AS3Class className="TL_6f18f81a2b824bf1a52297a547991affyxy" classType="PptTmline_xyxyxyxyxyxyxyxyxyxyxyxyxyxy" frameRate="30" normalSlide="1"><OnLoadCallBacks/><Audios/></AS3Class></slidexml>
			<clickAnimations></clickAnimations>
			<webObjectContents/>
			<flvContents/>
			<audios id="2" duration=" 8930">
				<media url="a24x2.mp3" startMsecs="0" duration="8930" startAtMSecs="0"/>
			</audios>
			<playbackActions></playbackActions>
			<slideTitle>@Chapitre 2 :  Les produits de santé Les modalités de leur commercialisation @</slideTitle>
			<notes isHTML="true"></notes>
			<slideThumbnail url="thumb.swf" frame="1"/>
			<slideSpeaker index="4"/>
		</slide>
		<slide id="414" showInTOC="" inSequence="" frameRate="30" totalFrames="30" usePptxSlideDur="0" lockInteractionSlide="false" isHiddenInteractionSl="false" isWrongInteractionSl="false" swfConvertorEngine="Nova" slideDuration="12.91" advance="auto" blockMovement="false" hideplaybar="false" type="normal">
			<content url="Slide1.swf" id="414"/>
			<backdrop displayBgSp="true"/>
			<master id="2" frameNum="0"/>
			<layout id="2" frameNum="0"/>
			<slidexml><AS3Class className="TL_648cde6868c8471f9f52efa233c72023yxy" classType="PptTmline_xyxyxyxyxyxyxyxyxyxyxyxyxyxy" frameRate="30" normalSlide="1"><OnLoadCallBacks/><Audios/></AS3Class></slidexml>
			<clickAnimations></clickAnimations>
			<webObjectContents/>
			<flvContents/>
			<audios id="3" duration=" 12910">
				<media url="a24x3.mp3" startMsecs="0" duration="12910" startAtMSecs="0"/>
			</audios>
			<playbackActions></playbackActions>
			<slideTitle>@@</slideTitle>
			<notes isHTML="true"></notes>
			<slideThumbnail url="thumb.swf" frame="2"/>
			<slideSpeaker index="4"/>
		</slide>
		<slide id="415" showInTOC="" inSequence="" frameRate="30" totalFrames="30" usePptxSlideDur="0" lockInteractionSlide="false" isHiddenInteractionSl="false" isWrongInteractionSl="false" swfConvertorEngine="Nova" slideDuration="46.02" advance="auto" blockMovement="false" hideplaybar="false" type="normal">
			<content url="Slide2.swf" id="415"/>
			<backdrop displayBgSp="true"/>
			<master id="2" frameNum="0"/>
			<layout id="2" frameNum="0"/>
			<slidexml><AS3Class className="TL_624a00f92668464e927ed57182d02546yxy" classType="PptTmline_xyxyxyxyxyxyxyxyxyxyxyxyxyxy" frameRate="30" normalSlide="1"><OnLoadCallBacks/><Audios/></AS3Class></slidexml>
			<clickAnimations></clickAnimations>
			<webObjectContents/>
			<flvContents/>
			<audios id="4" duration=" 46020">
				<media url="a24x4.mp3" startMsecs="0" duration="46020" startAtMSecs="0"/>
			</audios>
			<playbackActions></playbackActions>
			<slideTitle>@@</slideTitle>
			<notes isHTML="true"></notes>
			<slideThumbnail url="thumb.swf" frame="3"/>
			<slideSpeaker index="4"/>
		</slide>
		<slide id="416" showInTOC="" inSequence="" frameRate="30" totalFrames="30" usePptxSlideDur="0" lockInteractionSlide="false" isHiddenInteractionSl="false" isWrongInteractionSl="false" swfConvertorEngine="Nova" slideDuration="23.56" advance="auto" blockMovement="false" hideplaybar="false" type="normal">
			<content url="Slide3.swf" id="416"/>
			<backdrop displayBgSp="true"/>
			<master id="2" frameNum="0"/>
			<layout id="2" frameNum="0"/>
			<slidexml><AS3Class className="TL_b521730e5499436787c0c586c1888415yxy" classType="PptTmline_xyxyxyxyxyxyxyxyxyxyxyxyxyxy" frameRate="30" normalSlide="1"><OnLoadCallBacks/><Audios/></AS3Class></slidexml>
			<clickAnimations></clickAnimations>
			<webObjectContents/>
			<flvContents/>
			<audios id="5" duration=" 23560">
				<media url="a24x5.mp3" startMsecs="0" duration="23560" startAtMSecs="0"/>
			</audios>
			<playbackActions></playbackActions>
			<slideTitle>@@</slideTitle>
			<notes isHTML="true"></notes>
			<slideThumbnail url="thumb.swf" frame="4"/>
			<slideSpeaker index="4"/>
		</slide>
		<slide id="417" showInTOC="" inSequence="" frameRate="30" totalFrames="30" usePptxSlideDur="0" lockInteractionSlide="false" isHiddenInteractionSl="false" isWrongInteractionSl="false" swfConvertorEngine="Nova" slideDuration="40.54" advance="auto" blockMovement="false" hideplaybar="false" type="normal">
			<content url="Slide4.swf" id="417"/>
			<backdrop displayBgSp="true"/>
			<master id="2" frameNum="0"/>
			<layout id="2" frameNum="0"/>
			<slidexml><AS3Class className="TL_73539568331d47b4afb72e3779b55e5dyxy" classType="PptTmline_xyxyxyxyxyxyxyxyxyxyxyxyxyxy" frameRate="30" normalSlide="1"><OnLoadCallBacks/><Audios/></AS3Class></slidexml>
			<clickAnimations></clickAnimations>
			<webObjectContents/>
			<flvContents/>
			<audios id="6" duration=" 40540">
				<media url="a24x6.mp3" startMsecs="0" duration="40540" startAtMSecs="0"/>
			</audios>
			<playbackActions></playbackActions>
			<slideTitle>@@</slideTitle>
			<notes isHTML="true"></notes>
			<slideThumbnail url="thumb.swf" frame="5"/>
			<slideSpeaker index="4"/>
		</slide>
		<slide id="418" showInTOC="" inSequence="" frameRate="30" totalFrames="30" usePptxSlideDur="0" lockInteractionSlide="false" isHiddenInteractionSl="false" isWrongInteractionSl="false" swfConvertorEngine="Nova" slideDuration="7.38" advance="auto" blockMovement="false" hideplaybar="false" type="normal">
			<content url="Slide5.swf" id="418"/>
			<backdrop displayBgSp="true"/>
			<master id="2" frameNum="0"/>
			<layout id="2" frameNum="0"/>
			<slidexml><AS3Class className="TL_34be0c03bdbd49a3bcdeac686ca6bc9byxy" classType="PptTmline_xyxyxyxyxyxyxyxyxyxyxyxyxyxy" frameRate="30" normalSlide="1"><OnLoadCallBacks/><Audios/></AS3Class></slidexml>
			<clickAnimations></clickAnimations>
			<webObjectContents/>
			<flvContents/>
			<audios id="7" duration=" 7380">
				<media url="a24x7.mp3" startMsecs="0" duration="7380" startAtMSecs="0"/>
			</audios>
			<playbackActions></playbackActions>
			<slideTitle>@@</slideTitle>
			<notes isHTML="true"></notes>
			<slideThumbnail url="thumb.swf" frame="6"/>
			<slideSpeaker index="4"/>
		</slide>
		<slide id="419" showInTOC="" inSequence="" frameRate="30" totalFrames="30" usePptxSlideDur="0" lockInteractionSlide="false" isHiddenInteractionSl="false" isWrongInteractionSl="false" swfConvertorEngine="Nova" slideDuration="6.26" advance="auto" blockMovement="false" hideplaybar="false" type="normal">
			<content url="Slide6.swf" id="419"/>
			<backdrop displayBgSp="true"/>
			<master id="2" frameNum="0"/>
			<layout id="2" frameNum="0"/>
			<slidexml><AS3Class className="TL_c019325994654aa0b383594ea4d7abc3yxy" classType="PptTmline_xyxyxyxyxyxyxyxyxyxyxyxyxyxy" frameRate="30" normalSlide="1"><OnLoadCallBacks/><Audios/></AS3Class></slidexml>
			<clickAnimations></clickAnimations>
			<webObjectContents/>
			<flvContents/>
			<audios id="8" duration=" 6260">
				<media url="a24x8.mp3" startMsecs="0" duration="6260" startAtMSecs="0"/>
			</audios>
			<playbackActions></playbackActions>
			<slideTitle>@@</slideTitle>
			<notes isHTML="true"></notes>
			<slideThumbnail url="thumb.swf" frame="7"/>
			<slideSpeaker index="4"/>
		</slide>
		<slide id="420" showInTOC="" inSequence="" frameRate="30" totalFrames="30" usePptxSlideDur="0" lockInteractionSlide="false" isHiddenInteractionSl="false" isWrongInteractionSl="false" swfConvertorEngine="Nova" slideDuration="40.21" advance="auto" blockMovement="false" hideplaybar="false" type="normal">
			<content url="Slide7.swf" id="420"/>
			<backdrop displayBgSp="true"/>
			<master id="2" frameNum="0"/>
			<layout id="2" frameNum="0"/>
			<slidexml><AS3Class className="TL_b5aafe69ce1346ae895c3e7d735c20e1yxy" classType="PptTmline_xyxyxyxyxyxyxyxyxyxyxyxyxyxy" frameRate="30" normalSlide="1"><OnLoadCallBacks/><Audios/></AS3Class></slidexml>
			<clickAnimations></clickAnimations>
			<webObjectContents/>
			<flvContents/>
			<audios id="9" duration=" 40210">
				<media url="a24x9.mp3" startMsecs="0" duration="40210" startAtMSecs="0"/>
			</audios>
			<playbackActions></playbackActions>
			<slideTitle>@@</slideTitle>
			<notes isHTML="true"></notes>
			<slideThumbnail url="thumb.swf" frame="8"/>
			<slideSpeaker index="4"/>
		</slide>
		<slide id="421" showInTOC="" inSequence="" frameRate="30" totalFrames="30" usePptxSlideDur="0" lockInteractionSlide="false" isHiddenInteractionSl="false" isWrongInteractionSl="false" swfConvertorEngine="Nova" slideDuration="42.79" advance="auto" blockMovement="false" hideplaybar="false" type="normal">
			<content url="Slide8.swf" id="421"/>
			<backdrop displayBgSp="true"/>
			<master id="2" frameNum="0"/>
			<layout id="2" frameNum="0"/>
			<slidexml><AS3Class className="TL_c9c15ad13c304a6ea792d9fa43762473yxy" classType="PptTmline_xyxyxyxyxyxyxyxyxyxyxyxyxyxy" frameRate="30" normalSlide="1"><OnLoadCallBacks/><Audios/></AS3Class></slidexml>
			<clickAnimations></clickAnimations>
			<webObjectContents/>
			<flvContents/>
			<audios id="10" duration=" 42790">
				<media url="a24x10.mp3" startMsecs="0" duration="42790" startAtMSecs="0"/>
			</audios>
			<playbackActions></playbackActions>
			<slideTitle>@@</slideTitle>
			<notes isHTML="true"></notes>
			<slideThumbnail url="thumb.swf" frame="9"/>
			<slideSpeaker index="4"/>
		</slide>
		<slide id="422" showInTOC="" inSequence="" frameRate="30" totalFrames="30" usePptxSlideDur="0" lockInteractionSlide="false" isHiddenInteractionSl="false" isWrongInteractionSl="false" swfConvertorEngine="Nova" slideDuration="51.38" advance="auto" blockMovement="false" hideplaybar="false" type="normal">
			<content url="Slide9.swf" id="422"/>
			<backdrop displayBgSp="true"/>
			<master id="2" frameNum="0"/>
			<layout id="2" frameNum="0"/>
			<slidexml><AS3Class className="TL_13107a6313bb4baab35ffd5ebee42578yxy" classType="PptTmline_xyxyxyxyxyxyxyxyxyxyxyxyxyxy" frameRate="30" normalSlide="1"><OnLoadCallBacks/><Audios/></AS3Class></slidexml>
			<clickAnimations></clickAnimations>
			<webObjectContents/>
			<flvContents/>
			<audios id="11" duration=" 51380">
				<media url="a24x11.mp3" startMsecs="0" duration="51380" startAtMSecs="0"/>
			</audios>
			<playbackActions></playbackActions>
			<slideTitle>@@</slideTitle>
			<notes isHTML="true"></notes>
			<slideThumbnail url="thumb.swf" frame="10"/>
			<slideSpeaker index="4"/>
		</slide>
		<slide id="423" showInTOC="" inSequence="" frameRate="30" totalFrames="30" usePptxSlideDur="0" lockInteractionSlide="false" isHiddenInteractionSl="false" isWrongInteractionSl="false" swfConvertorEngine="Nova" slideDuration="26.87" advance="auto" blockMovement="false" hideplaybar="false" type="normal">
			<content url="Slide10.swf" id="423"/>
			<backdrop displayBgSp="true"/>
			<master id="2" frameNum="0"/>
			<layout id="2" frameNum="0"/>
			<slidexml><AS3Class className="TL_c8ba16dc5509401d94f9ff115779c167yxy" classType="PptTmline_xyxyxyxyxyxyxyxyxyxyxyxyxyxy" frameRate="30" normalSlide="1"><OnLoadCallBacks/><Audios/></AS3Class></slidexml>
			<clickAnimations></clickAnimations>
			<webObjectContents/>
			<flvContents/>
			<audios id="12" duration=" 26870">
				<media url="a24x12.mp3" startMsecs="0" duration="26870" startAtMSecs="0"/>
			</audios>
			<playbackActions></playbackActions>
			<slideTitle>@@</slideTitle>
			<notes isHTML="true"></notes>
			<slideThumbnail url="thumb.swf" frame="11"/>
			<slideSpeaker index="4"/>
		</slide>
		<slide id="424" showInTOC="" inSequence="" frameRate="30" totalFrames="30" usePptxSlideDur="0" lockInteractionSlide="false" isHiddenInteractionSl="false" isWrongInteractionSl="false" swfConvertorEngine="Nova" slideDuration="39.48" advance="auto" blockMovement="false" hideplaybar="false" type="normal">
			<content url="Slide11.swf" id="424"/>
			<backdrop displayBgSp="true"/>
			<master id="2" frameNum="0"/>
			<layout id="2" frameNum="0"/>
			<slidexml><AS3Class className="TL_4ef5151a5de344ec88920fb9fa6ffe73yxy" classType="PptTmline_xyxyxyxyxyxyxyxyxyxyxyxyxyxy" frameRate="30" normalSlide="1"><OnLoadCallBacks/><Audios/></AS3Class></slidexml>
			<clickAnimations></clickAnimations>
			<webObjectContents/>
			<flvContents/>
			<audios id="13" duration=" 39480">
				<media url="a24x13.mp3" startMsecs="0" duration="39480" startAtMSecs="0"/>
			</audios>
			<playbackActions></playbackActions>
			<slideTitle>@@</slideTitle>
			<notes isHTML="true"></notes>
			<slideThumbnail url="thumb.swf" frame="12"/>
			<slideSpeaker index="4"/>
		</slide>
		<slide id="425" showInTOC="" inSequence="" frameRate="30" totalFrames="30" usePptxSlideDur="0" lockInteractionSlide="false" isHiddenInteractionSl="false" isWrongInteractionSl="false" swfConvertorEngine="Nova" slideDuration="46.2" advance="auto" blockMovement="false" hideplaybar="false" type="normal">
			<content url="Slide12.swf" id="425"/>
			<backdrop displayBgSp="true"/>
			<master id="2" frameNum="0"/>
			<layout id="2" frameNum="0"/>
			<slidexml><AS3Class className="TL_51f702dbb86a4daa82fcf1a4c55fd0b3yxy" classType="PptTmline_xyxyxyxyxyxyxyxyxyxyxyxyxyxy" frameRate="30" normalSlide="1"><OnLoadCallBacks/><Audios/></AS3Class></slidexml>
			<clickAnimations></clickAnimations>
			<webObjectContents/>
			<flvContents/>
			<audios id="14" duration=" 46200">
				<media url="a24x14.mp3" startMsecs="0" duration="46200" startAtMSecs="0"/>
			</audios>
			<playbackActions></playbackActions>
			<slideTitle>@@</slideTitle>
			<notes isHTML="true"></notes>
			<slideThumbnail url="thumb.swf" frame="13"/>
			<slideSpeaker index="4"/>
		</slide>
		<slide id="426" showInTOC="" inSequence="" frameRate="30" totalFrames="30" usePptxSlideDur="0" lockInteractionSlide="false" isHiddenInteractionSl="false" isWrongInteractionSl="false" swfConvertorEngine="Nova" slideDuration="46.62" advance="auto" blockMovement="false" hideplaybar="false" type="normal">
			<content url="Slide13.swf" id="426"/>
			<backdrop displayBgSp="true"/>
			<master id="2" frameNum="0"/>
			<layout id="2" frameNum="0"/>
			<slidexml><AS3Class className="TL_aaa42b133c47496ea977e6824a6483fcyxy" classType="PptTmline_xyxyxyxyxyxyxyxyxyxyxyxyxyxy" frameRate="30" normalSlide="1"><OnLoadCallBacks/><Audios/></AS3Class></slidexml>
			<clickAnimations></clickAnimations>
			<webObjectContents/>
			<flvContents/>
			<audios id="15" duration=" 46620">
				<media url="a24x15.mp3" startMsecs="0" duration="46620" startAtMSecs="0"/>
			</audios>
			<playbackActions></playbackActions>
			<slideTitle>@@</slideTitle>
			<notes isHTML="true"></notes>
			<slideThumbnail url="thumb.swf" frame="14"/>
			<slideSpeaker index="4"/>
		</slide>
		<slide id="427" showInTOC="" inSequence="" frameRate="30" totalFrames="30" usePptxSlideDur="0" lockInteractionSlide="false" isHiddenInteractionSl="false" isWrongInteractionSl="false" swfConvertorEngine="Nova" slideDuration="43.08" advance="auto" blockMovement="false" hideplaybar="false" type="normal">
			<content url="Slide14.swf" id="427"/>
			<backdrop displayBgSp="true"/>
			<master id="2" frameNum="0"/>
			<layout id="2" frameNum="0"/>
			<slidexml><AS3Class className="TL_2b3ec55a8d9148f1ba01e6672ce241c9yxy" classType="PptTmline_xyxyxyxyxyxyxyxyxyxyxyxyxyxy" frameRate="30" normalSlide="1"><OnLoadCallBacks/><Audios/></AS3Class></slidexml>
			<clickAnimations></clickAnimations>
			<webObjectContents/>
			<flvContents/>
			<audios id="16" duration=" 43080">
				<media url="a24x16.mp3" startMsecs="0" duration="43080" startAtMSecs="0"/>
			</audios>
			<playbackActions></playbackActions>
			<slideTitle>@@</slideTitle>
			<notes isHTML="true"></notes>
			<slideThumbnail url="thumb.swf" frame="15"/>
			<slideSpeaker index="4"/>
		</slide>
		<slide id="428" showInTOC="" inSequence="" frameRate="30" totalFrames="30" usePptxSlideDur="0" lockInteractionSlide="false" isHiddenInteractionSl="false" isWrongInteractionSl="false" swfConvertorEngine="Nova" slideDuration="29.65" advance="auto" blockMovement="false" hideplaybar="false" type="normal">
			<content url="Slide15.swf" id="428"/>
			<backdrop displayBgSp="true"/>
			<master id="2" frameNum="0"/>
			<layout id="2" frameNum="0"/>
			<slidexml><AS3Class className="TL_fba85e522e4f4e9ebf0b17a9ca69161fyxy" classType="PptTmline_xyxyxyxyxyxyxyxyxyxyxyxyxyxy" frameRate="30" normalSlide="1"><OnLoadCallBacks/><Audios/></AS3Class></slidexml>
			<clickAnimations></clickAnimations>
			<webObjectContents/>
			<flvContents/>
			<audios id="17" duration=" 29650">
				<media url="a24x17.mp3" startMsecs="0" duration="29650" startAtMSecs="0"/>
			</audios>
			<playbackActions></playbackActions>
			<slideTitle>@@</slideTitle>
			<notes isHTML="true"></notes>
			<slideThumbnail url="thumb.swf" frame="16"/>
			<slideSpeaker index="4"/>
		</slide>
		<slide id="429" showInTOC="" inSequence="" frameRate="30" totalFrames="30" usePptxSlideDur="0" lockInteractionSlide="false" isHiddenInteractionSl="false" isWrongInteractionSl="false" swfConvertorEngine="Nova" slideDuration="14.2" advance="auto" blockMovement="false" hideplaybar="false" type="normal">
			<content url="Slide16.swf" id="429"/>
			<backdrop displayBgSp="true"/>
			<master id="2" frameNum="0"/>
			<layout id="2" frameNum="0"/>
			<slidexml><AS3Class className="TL_666c0e74dd4b4df2bac69c18174acc0cyxy" classType="PptTmline_xyxyxyxyxyxyxyxyxyxyxyxyxyxy" frameRate="30" normalSlide="1"><OnLoadCallBacks/><Audios/></AS3Class></slidexml>
			<clickAnimations></clickAnimations>
			<webObjectContents/>
			<flvContents/>
			<audios id="18" duration=" 14200">
				<media url="a24x18.mp3" startMsecs="0" duration="14200" startAtMSecs="0"/>
			</audios>
			<playbackActions></playbackActions>
			<slideTitle>@@</slideTitle>
			<notes isHTML="true"></notes>
			<slideThumbnail url="thumb.swf" frame="17"/>
			<slideSpeaker index="4"/>
		</slide>
		<slide id="430" showInTOC="" inSequence="" frameRate="30" totalFrames="30" usePptxSlideDur="0" lockInteractionSlide="false" isHiddenInteractionSl="false" isWrongInteractionSl="false" swfConvertorEngine="Nova" slideDuration="32.82" advance="auto" blockMovement="false" hideplaybar="false" type="normal">
			<content url="Slide17.swf" id="430"/>
			<backdrop displayBgSp="true"/>
			<master id="2" frameNum="0"/>
			<layout id="2" frameNum="0"/>
			<slidexml><AS3Class className="TL_db36d81a5a784fa59d0c648bc2041e24yxy" classType="PptTmline_xyxyxyxyxyxyxyxyxyxyxyxyxyxy" frameRate="30" normalSlide="1"><OnLoadCallBacks/><Audios/></AS3Class></slidexml>
			<clickAnimations></clickAnimations>
			<webObjectContents/>
			<flvContents/>
			<audios id="19" duration=" 32820">
				<media url="a24x19.mp3" startMsecs="0" duration="32820" startAtMSecs="0"/>
			</audios>
			<playbackActions></playbackActions>
			<slideTitle>@@</slideTitle>
			<notes isHTML="true"></notes>
			<slideThumbnail url="thumb.swf" frame="18"/>
			<slideSpeaker index="4"/>
		</slide>
		<slide id="431" showInTOC="" inSequence="" frameRate="30" totalFrames="30" usePptxSlideDur="0" lockInteractionSlide="false" isHiddenInteractionSl="false" isWrongInteractionSl="false" swfConvertorEngine="Nova" slideDuration="42.2" advance="auto" blockMovement="false" hideplaybar="false" type="normal">
			<content url="Slide18.swf" id="431"/>
			<backdrop displayBgSp="true"/>
			<master id="2" frameNum="0"/>
			<layout id="2" frameNum="0"/>
			<slidexml><AS3Class className="TL_edb8c7faeaca4160a6426a1a19405b32yxy" classType="PptTmline_xyxyxyxyxyxyxyxyxyxyxyxyxyxy" frameRate="30" normalSlide="1"><OnLoadCallBacks/><Audios/></AS3Class></slidexml>
			<clickAnimations></clickAnimations>
			<webObjectContents/>
			<flvContents/>
			<audios id="20" duration=" 42200">
				<media url="a24x20.mp3" startMsecs="0" duration="42200" startAtMSecs="0"/>
			</audios>
			<playbackActions></playbackActions>
			<slideTitle>@@</slideTitle>
			<notes isHTML="true"></notes>
			<slideThumbnail url="thumb.swf" frame="19"/>
			<slideSpeaker index="4"/>
		</slide>
		<slide id="460" showInTOC="" inSequence="" frameRate="30" totalFrames="30" usePptxSlideDur="0" lockInteractionSlide="false" isHiddenInteractionSl="false" isWrongInteractionSl="false" swfConvertorEngine="Nova" slideDuration="52.04" advance="auto" blockMovement="false" hideplaybar="false" type="normal">
			<content url="Slide19.swf" id="460"/>
			<backdrop displayBgSp="true"/>
			<master id="2" frameNum="0"/>
			<layout id="2" frameNum="0"/>
			<slidexml><AS3Class className="TL_f6041899c4fa4da897eb430e340a1aafyxy" classType="PptTmline_xyxyxyxyxyxyxyxyxyxyxyxyxyxy" frameRate="30" normalSlide="1"><OnLoadCallBacks/><Audios/></AS3Class></slidexml>
			<clickAnimations></clickAnimations>
			<webObjectContents/>
			<flvContents/>
			<audios id="21" duration=" 52040">
				<media url="a24x21.mp3" startMsecs="0" duration="52040" startAtMSecs="0"/>
			</audios>
			<playbackActions></playbackActions>
			<slideTitle>@@</slideTitle>
			<notes isHTML="true"></notes>
			<slideThumbnail url="thumb.swf" frame="20"/>
			<slideSpeaker index="4"/>
		</slide>
		<slide id="461" showInTOC="" inSequence="" frameRate="30" totalFrames="30" usePptxSlideDur="0" lockInteractionSlide="false" isHiddenInteractionSl="false" isWrongInteractionSl="false" swfConvertorEngine="Nova" slideDuration="51.62" advance="auto" blockMovement="false" hideplaybar="false" type="normal">
			<content url="Slide20.swf" id="461"/>
			<backdrop displayBgSp="true"/>
			<master id="2" frameNum="0"/>
			<layout id="2" frameNum="0"/>
			<slidexml><AS3Class className="TL_21329307f3ab457c8acd7f7a539795f4yxy" classType="PptTmline_xyxyxyxyxyxyxyxyxyxyxyxyxyxy" frameRate="30" normalSlide="1"><OnLoadCallBacks/><Audios/></AS3Class></slidexml>
			<clickAnimations></clickAnimations>
			<webObjectContents/>
			<flvContents/>
			<audios id="22" duration=" 51620">
				<media url="a24x22.mp3" startMsecs="0" duration="51620" startAtMSecs="0"/>
			</audios>
			<playbackActions></playbackActions>
			<slideTitle>@@</slideTitle>
			<notes isHTML="true"></notes>
			<slideThumbnail url="thumb.swf" frame="21"/>
			<slideSpeaker index="4"/>
		</slide>
		<slide id="433" showInTOC="" inSequence="" frameRate="30" totalFrames="30" usePptxSlideDur="0" lockInteractionSlide="false" isHiddenInteractionSl="false" isWrongInteractionSl="false" swfConvertorEngine="Nova" slideDuration="44.91" advance="auto" blockMovement="false" hideplaybar="false" type="normal">
			<content url="Slide21.swf" id="433"/>
			<backdrop displayBgSp="true"/>
			<master id="2" frameNum="0"/>
			<layout id="2" frameNum="0"/>
			<slidexml><AS3Class className="TL_e2f51eb66fd24be4b3bf0a6380c9c0e5yxy" classType="PptTmline_xyxyxyxyxyxyxyxyxyxyxyxyxyxy" frameRate="30" normalSlide="1"><OnLoadCallBacks/><Audios/></AS3Class></slidexml>
			<clickAnimations></clickAnimations>
			<webObjectContents/>
			<flvContents/>
			<audios id="23" duration=" 44910">
				<media url="a24x23.mp3" startMsecs="0" duration="44910" startAtMSecs="0"/>
			</audios>
			<playbackActions></playbackActions>
			<slideTitle>@@</slideTitle>
			<notes isHTML="true"></notes>
			<slideThumbnail url="thumb.swf" frame="22"/>
			<slideSpeaker index="4"/>
		</slide>
		<slide id="434" showInTOC="" inSequence="" frameRate="30" totalFrames="30" usePptxSlideDur="0" lockInteractionSlide="false" isHiddenInteractionSl="false" isWrongInteractionSl="false" swfConvertorEngine="Nova" slideDuration="33.95" advance="auto" blockMovement="false" hideplaybar="false" type="normal">
			<content url="Slide22.swf" id="434"/>
			<backdrop displayBgSp="true"/>
			<master id="2" frameNum="0"/>
			<layout id="2" frameNum="0"/>
			<slidexml><AS3Class className="TL_dfd0080a08e24d23bda68610d0b783cbyxy" classType="PptTmline_xyxyxyxyxyxyxyxyxyxyxyxyxyxy" frameRate="30" normalSlide="1"><OnLoadCallBacks/><Audios/></AS3Class></slidexml>
			<clickAnimations></clickAnimations>
			<webObjectContents/>
			<flvContents/>
			<audios id="24" duration=" 33950">
				<media url="a24x24.mp3" startMsecs="0" duration="33950" startAtMSecs="0"/>
			</audios>
			<playbackActions></playbackActions>
			<slideTitle>@@</slideTitle>
			<notes isHTML="true"></notes>
			<slideThumbnail url="thumb.swf" frame="23"/>
			<slideSpeaker index="4"/>
		</slide>
		<slide id="435" showInTOC="" inSequence="" frameRate="30" totalFrames="30" usePptxSlideDur="0" lockInteractionSlide="false" isHiddenInteractionSl="false" isWrongInteractionSl="false" swfConvertorEngine="Nova" slideDuration="42.71" advance="auto" blockMovement="false" hideplaybar="false" type="normal">
			<content url="Slide23.swf" id="435"/>
			<backdrop displayBgSp="true"/>
			<master id="2" frameNum="0"/>
			<layout id="2" frameNum="0"/>
			<slidexml><AS3Class className="TL_81dc0ac5c8ca4d78aa2a1f82c12b2438yxy" classType="PptTmline_xyxyxyxyxyxyxyxyxyxyxyxyxyxy" frameRate="30" normalSlide="1"><OnLoadCallBacks/><Audios/></AS3Class></slidexml>
			<clickAnimations></clickAnimations>
			<webObjectContents/>
			<flvContents/>
			<audios id="25" duration=" 42710">
				<media url="a24x25.mp3" startMsecs="0" duration="42710" startAtMSecs="0"/>
			</audios>
			<playbackActions></playbackActions>
			<slideTitle>@@</slideTitle>
			<notes isHTML="true"></notes>
			<slideThumbnail url="thumb.swf" frame="24"/>
			<slideSpeaker index="4"/>
		</slide>
		<slide id="437" showInTOC="" inSequence="" frameRate="30" totalFrames="30" usePptxSlideDur="0" lockInteractionSlide="false" isHiddenInteractionSl="false" isWrongInteractionSl="false" swfConvertorEngine="Nova" slideDuration="13.27" advance="auto" blockMovement="false" hideplaybar="false" type="normal">
			<content url="Slide24.swf" id="437"/>
			<backdrop displayBgSp="true"/>
			<master id="2" frameNum="0"/>
			<layout id="2" frameNum="0"/>
			<slidexml><AS3Class className="TL_22421279767a4e1094493f5528654414yxy" classType="PptTmline_xyxyxyxyxyxyxyxyxyxyxyxyxyxy" frameRate="30" normalSlide="1"><OnLoadCallBacks/><Audios/></AS3Class></slidexml>
			<clickAnimations></clickAnimations>
			<webObjectContents/>
			<flvContents/>
			<audios id="26" duration=" 13270">
				<media url="a24x26.mp3" startMsecs="0" duration="13270" startAtMSecs="0"/>
			</audios>
			<playbackActions></playbackActions>
			<slideTitle>@@</slideTitle>
			<notes isHTML="true"></notes>
			<slideThumbnail url="thumb.swf" frame="25"/>
			<slideSpeaker index="4"/>
		</slide>
		<slide id="436" showInTOC="" inSequence="" frameRate="30" totalFrames="30" usePptxSlideDur="0" lockInteractionSlide="false" isHiddenInteractionSl="false" isWrongInteractionSl="false" swfConvertorEngine="Nova" slideDuration="11.49" advance="auto" blockMovement="false" hideplaybar="false" type="normal">
			<content url="Slide25.swf" id="436"/>
			<backdrop displayBgSp="true"/>
			<master id="2" frameNum="0"/>
			<layout id="2" frameNum="0"/>
			<slidexml><AS3Class className="TL_9493535331154b02961a134440729e10yxy" classType="PptTmline_xyxyxyxyxyxyxyxyxyxyxyxyxyxy" frameRate="30" normalSlide="1"><OnLoadCallBacks/><Audios/></AS3Class></slidexml>
			<clickAnimations></clickAnimations>
			<webObjectContents/>
			<flvContents/>
			<audios id="27" duration=" 11490">
				<media url="a24x27.mp3" startMsecs="0" duration="11490" startAtMSecs="0"/>
			</audios>
			<playbackActions></playbackActions>
			<slideTitle>@@</slideTitle>
			<notes isHTML="true"></notes>
			<slideThumbnail url="thumb.swf" frame="26"/>
			<slideSpeaker index="4"/>
		</slide>
		<slide id="439" showInTOC="" inSequence="" frameRate="30" totalFrames="30" usePptxSlideDur="0" lockInteractionSlide="false" isHiddenInteractionSl="false" isWrongInteractionSl="false" swfConvertorEngine="Nova" slideDuration="38.47" advance="auto" blockMovement="false" hideplaybar="false" type="normal">
			<content url="Slide26.swf" id="439"/>
			<backdrop displayBgSp="true"/>
			<master id="2" frameNum="0"/>
			<layout id="2" frameNum="0"/>
			<slidexml><AS3Class className="TL_21e4e1ddd08c4e9eb6e91d92b92efd2byxy" classType="PptTmline_xyxyxyxyxyxyxyxyxyxyxyxyxyxy" frameRate="30" normalSlide="1"><OnLoadCallBacks/><Audios/></AS3Class></slidexml>
			<clickAnimations></clickAnimations>
			<webObjectContents/>
			<flvContents/>
			<audios id="28" duration=" 38470">
				<media url="a24x28.mp3" startMsecs="0" duration="38470" startAtMSecs="0"/>
			</audios>
			<playbackActions></playbackActions>
			<slideTitle>@@</slideTitle>
			<notes isHTML="true"></notes>
			<slideThumbnail url="thumb.swf" frame="27"/>
			<slideSpeaker index="4"/>
		</slide>
		<slide id="438" showInTOC="" inSequence="" frameRate="30" totalFrames="30" usePptxSlideDur="0" lockInteractionSlide="false" isHiddenInteractionSl="false" isWrongInteractionSl="false" swfConvertorEngine="Nova" slideDuration="6.21" advance="auto" blockMovement="false" hideplaybar="false" type="normal">
			<content url="Slide27.swf" id="438"/>
			<backdrop displayBgSp="true"/>
			<master id="2" frameNum="0"/>
			<layout id="2" frameNum="0"/>
			<slidexml><AS3Class className="TL_a0b357187aa341938e9e8064f0eba79byxy" classType="PptTmline_xyxyxyxyxyxyxyxyxyxyxyxyxyxy" frameRate="30" normalSlide="1"><OnLoadCallBacks/><Audios/></AS3Class></slidexml>
			<clickAnimations></clickAnimations>
			<webObjectContents/>
			<flvContents/>
			<audios id="29" duration=" 6210">
				<media url="a24x29.mp3" startMsecs="0" duration="6210" startAtMSecs="0"/>
			</audios>
			<playbackActions></playbackActions>
			<slideTitle>@@</slideTitle>
			<notes isHTML="true"></notes>
			<slideThumbnail url="thumb.swf" frame="28"/>
			<slideSpeaker index="4"/>
		</slide>
		<slide id="440" showInTOC="" inSequence="" frameRate="30" totalFrames="30" usePptxSlideDur="0" lockInteractionSlide="false" isHiddenInteractionSl="false" isWrongInteractionSl="false" swfConvertorEngine="Nova" slideDuration="67.01" advance="auto" blockMovement="false" hideplaybar="false" type="normal">
			<content url="Slide28.swf" id="440"/>
			<backdrop displayBgSp="true"/>
			<master id="2" frameNum="0"/>
			<layout id="2" frameNum="0"/>
			<slidexml><AS3Class className="TL_a042eaa8120e4606bf9dcecf9ff0ffffyxy" classType="PptTmline_xyxyxyxyxyxyxyxyxyxyxyxyxyxy" frameRate="30" normalSlide="1"><OnLoadCallBacks/><Audios/></AS3Class></slidexml>
			<clickAnimations></clickAnimations>
			<webObjectContents/>
			<flvContents/>
			<audios id="30" duration=" 67010">
				<media url="a24x30.mp3" startMsecs="0" duration="67010" startAtMSecs="0"/>
			</audios>
			<playbackActions></playbackActions>
			<slideTitle>@@</slideTitle>
			<notes isHTML="true"></notes>
			<slideThumbnail url="thumb.swf" frame="29"/>
			<slideSpeaker index="4"/>
		</slide>
		<slide id="462" showInTOC="" inSequence="" frameRate="30" totalFrames="30" usePptxSlideDur="0" lockInteractionSlide="false" isHiddenInteractionSl="false" isWrongInteractionSl="false" swfConvertorEngine="Nova" slideDuration="65.37" advance="auto" blockMovement="false" hideplaybar="false" type="normal">
			<content url="Slide29.swf" id="462"/>
			<backdrop displayBgSp="true"/>
			<master id="2" frameNum="0"/>
			<layout id="2" frameNum="0"/>
			<slidexml><AS3Class className="TL_f859c53236f34fd0895c37072fcd6044yxy" classType="PptTmline_xyxyxyxyxyxyxyxyxyxyxyxyxyxy" frameRate="30" normalSlide="1"><OnLoadCallBacks/><Audios/></AS3Class></slidexml>
			<clickAnimations></clickAnimations>
			<webObjectContents/>
			<flvContents/>
			<audios id="31" duration=" 65370">
				<media url="a24x31.mp3" startMsecs="0" duration="65370" startAtMSecs="0"/>
			</audios>
			<playbackActions></playbackActions>
			<slideTitle>@@</slideTitle>
			<notes isHTML="true"></notes>
			<slideThumbnail url="thumb.swf" frame="30"/>
			<slideSpeaker index="4"/>
		</slide>
		<slide id="442" showInTOC="" inSequence="" frameRate="30" totalFrames="30" usePptxSlideDur="0" lockInteractionSlide="false" isHiddenInteractionSl="false" isWrongInteractionSl="false" swfConvertorEngine="Nova" slideDuration="42.3" advance="auto" blockMovement="false" hideplaybar="false" type="normal">
			<content url="Slide30.swf" id="442"/>
			<backdrop displayBgSp="true"/>
			<master id="2" frameNum="0"/>
			<layout id="2" frameNum="0"/>
			<slidexml><AS3Class className="TL_278de267862640ac8d2bb539e9f1db78yxy" classType="PptTmline_xyxyxyxyxyxyxyxyxyxyxyxyxyxy" frameRate="30" normalSlide="1"><OnLoadCallBacks/><Audios/></AS3Class></slidexml>
			<clickAnimations></clickAnimations>
			<webObjectContents/>
			<flvContents/>
			<audios id="32" duration=" 42300">
				<media url="a24x32.mp3" startMsecs="0" duration="42300" startAtMSecs="0"/>
			</audios>
			<playbackActions></playbackActions>
			<slideTitle>@@</slideTitle>
			<notes isHTML="true"></notes>
			<slideThumbnail url="thumb.swf" frame="31"/>
			<slideSpeaker index="4"/>
		</slide>
		<slide id="443" showInTOC="" inSequence="" frameRate="30" totalFrames="30" usePptxSlideDur="0" lockInteractionSlide="false" isHiddenInteractionSl="false" isWrongInteractionSl="false" swfConvertorEngine="Nova" slideDuration="40.36" advance="auto" blockMovement="false" hideplaybar="false" type="normal">
			<content url="Slide31.swf" id="443"/>
			<backdrop displayBgSp="true"/>
			<master id="2" frameNum="0"/>
			<layout id="2" frameNum="0"/>
			<slidexml><AS3Class className="TL_ec931eaac4e44682b6a874328548c1e2yxy" classType="PptTmline_xyxyxyxyxyxyxyxyxyxyxyxyxyxy" frameRate="30" normalSlide="1"><OnLoadCallBacks/><Audios/></AS3Class></slidexml>
			<clickAnimations></clickAnimations>
			<webObjectContents/>
			<flvContents/>
			<audios id="33" duration=" 40360">
				<media url="a24x33.mp3" startMsecs="0" duration="40360" startAtMSecs="0"/>
			</audios>
			<playbackActions></playbackActions>
			<slideTitle>@@</slideTitle>
			<notes isHTML="true"></notes>
			<slideThumbnail url="thumb.swf" frame="32"/>
			<slideSpeaker index="4"/>
		</slide>
		<slide id="445" showInTOC="" inSequence="" frameRate="30" totalFrames="30" usePptxSlideDur="0" lockInteractionSlide="false" isHiddenInteractionSl="false" isWrongInteractionSl="false" swfConvertorEngine="Nova" slideDuration="22.23" advance="auto" blockMovement="false" hideplaybar="false" type="normal">
			<content url="Slide32.swf" id="445"/>
			<backdrop displayBgSp="true"/>
			<master id="2" frameNum="0"/>
			<layout id="2" frameNum="0"/>
			<slidexml><AS3Class className="TL_16b52578f63c4cdc8caf043c5e1554e4yxy" classType="PptTmline_xyxyxyxyxyxyxyxyxyxyxyxyxyxy" frameRate="30" normalSlide="1"><OnLoadCallBacks/><Audios/></AS3Class></slidexml>
			<clickAnimations></clickAnimations>
			<webObjectContents/>
			<flvContents/>
			<audios id="34" duration=" 22230">
				<media url="a24x34.mp3" startMsecs="0" duration="22230" startAtMSecs="0"/>
			</audios>
			<playbackActions></playbackActions>
			<slideTitle>@@</slideTitle>
			<notes isHTML="true"></notes>
			<slideThumbnail url="thumb.swf" frame="33"/>
			<slideSpeaker index="4"/>
		</slide>
		<slide id="446" showInTOC="" inSequence="" frameRate="30" totalFrames="30" usePptxSlideDur="0" lockInteractionSlide="false" isHiddenInteractionSl="false" isWrongInteractionSl="false" swfConvertorEngine="Nova" slideDuration="4.61" advance="auto" blockMovement="false" hideplaybar="false" type="normal">
			<content url="Slide33.swf" id="446"/>
			<backdrop displayBgSp="true"/>
			<master id="2" frameNum="0"/>
			<layout id="2" frameNum="0"/>
			<slidexml><AS3Class className="TL_3e6f780482714c989c754cb4ccd98001yxy" classType="PptTmline_xyxyxyxyxyxyxyxyxyxyxyxyxyxy" frameRate="30" normalSlide="1"><OnLoadCallBacks/><Audios/></AS3Class></slidexml>
			<clickAnimations></clickAnimations>
			<webObjectContents/>
			<flvContents/>
			<audios id="35" duration=" 4610">
				<media url="a24x35.mp3" startMsecs="0" duration="4610" startAtMSecs="0"/>
			</audios>
			<playbackActions></playbackActions>
			<slideTitle>@@</slideTitle>
			<notes isHTML="true"></notes>
			<slideThumbnail url="thumb.swf" frame="34"/>
			<slideSpeaker index="4"/>
		</slide>
		<slide id="447" showInTOC="" inSequence="" frameRate="30" totalFrames="30" usePptxSlideDur="0" lockInteractionSlide="false" isHiddenInteractionSl="false" isWrongInteractionSl="false" swfConvertorEngine="Nova" slideDuration="37.99" advance="auto" blockMovement="false" hideplaybar="false" type="normal">
			<content url="Slide34.swf" id="447"/>
			<backdrop displayBgSp="true"/>
			<master id="2" frameNum="0"/>
			<layout id="2" frameNum="0"/>
			<slidexml><AS3Class className="TL_4d8f35e4b2a6468ab760f22fbed2bba2yxy" classType="PptTmline_xyxyxyxyxyxyxyxyxyxyxyxyxyxy" frameRate="30" normalSlide="1"><OnLoadCallBacks/><Audios/></AS3Class></slidexml>
			<clickAnimations></clickAnimations>
			<webObjectContents/>
			<flvContents/>
			<audios id="36" duration=" 37990">
				<media url="a24x36.mp3" startMsecs="0" duration="37990" startAtMSecs="0"/>
			</audios>
			<playbackActions></playbackActions>
			<slideTitle>@@</slideTitle>
			<notes isHTML="true"></notes>
			<slideThumbnail url="thumb.swf" frame="35"/>
			<slideSpeaker index="4"/>
		</slide>
		<slide id="448" showInTOC="" inSequence="" frameRate="30" totalFrames="30" usePptxSlideDur="0" lockInteractionSlide="false" isHiddenInteractionSl="false" isWrongInteractionSl="false" swfConvertorEngine="Nova" slideDuration="40.98" advance="auto" blockMovement="false" hideplaybar="false" type="normal">
			<content url="Slide35.swf" id="448"/>
			<backdrop displayBgSp="true"/>
			<master id="2" frameNum="0"/>
			<layout id="2" frameNum="0"/>
			<slidexml><AS3Class className="TL_9a346ac1c7b14bafbf94ff54232ad3d3yxy" classType="PptTmline_xyxyxyxyxyxyxyxyxyxyxyxyxyxy" frameRate="30" normalSlide="1"><OnLoadCallBacks/><Audios/></AS3Class></slidexml>
			<clickAnimations></clickAnimations>
			<webObjectContents/>
			<flvContents/>
			<audios id="37" duration=" 40980">
				<media url="a24x37.mp3" startMsecs="0" duration="40980" startAtMSecs="0"/>
			</audios>
			<playbackActions></playbackActions>
			<slideTitle>@@</slideTitle>
			<notes isHTML="true"></notes>
			<slideThumbnail url="thumb.swf" frame="36"/>
			<slideSpeaker index="4"/>
		</slide>
		<slide id="449" showInTOC="" inSequence="" frameRate="30" totalFrames="30" usePptxSlideDur="0" lockInteractionSlide="false" isHiddenInteractionSl="false" isWrongInteractionSl="false" swfConvertorEngine="Nova" slideDuration="13.05" advance="auto" blockMovement="false" hideplaybar="false" type="normal">
			<content url="Slide36.swf" id="449"/>
			<backdrop displayBgSp="true"/>
			<master id="2" frameNum="0"/>
			<layout id="2" frameNum="0"/>
			<slidexml><AS3Class className="TL_b9b4a94bdfcc4a129595215dc07a2268yxy" classType="PptTmline_xyxyxyxyxyxyxyxyxyxyxyxyxyxy" frameRate="30" normalSlide="1"><OnLoadCallBacks/><Audios/></AS3Class></slidexml>
			<clickAnimations></clickAnimations>
			<webObjectContents/>
			<flvContents/>
			<audios id="38" duration=" 13050">
				<media url="a24x38.mp3" startMsecs="0" duration="13050" startAtMSecs="0"/>
			</audios>
			<playbackActions></playbackActions>
			<slideTitle>@@</slideTitle>
			<notes isHTML="true"></notes>
			<slideThumbnail url="thumb.swf" frame="37"/>
			<slideSpeaker index="4"/>
		</slide>
		<slide id="450" showInTOC="" inSequence="" frameRate="30" totalFrames="30" usePptxSlideDur="0" lockInteractionSlide="false" isHiddenInteractionSl="false" isWrongInteractionSl="false" swfConvertorEngine="Nova" slideDuration="49.91" advance="auto" blockMovement="false" hideplaybar="false" type="normal">
			<content url="Slide37.swf" id="450"/>
			<backdrop displayBgSp="true"/>
			<master id="2" frameNum="0"/>
			<layout id="2" frameNum="0"/>
			<slidexml><AS3Class className="TL_5598c7fd0fd945458144dca041e1229byxy" classType="PptTmline_xyxyxyxyxyxyxyxyxyxyxyxyxyxy" frameRate="30" normalSlide="1"><OnLoadCallBacks/><Audios/></AS3Class></slidexml>
			<clickAnimations></clickAnimations>
			<webObjectContents/>
			<flvContents/>
			<audios id="39" duration=" 49910">
				<media url="a24x39.mp3" startMsecs="0" duration="49910" startAtMSecs="0"/>
			</audios>
			<playbackActions></playbackActions>
			<slideTitle>@@</slideTitle>
			<notes isHTML="true"></notes>
			<slideThumbnail url="thumb.swf" frame="38"/>
			<slideSpeaker index="4"/>
		</slide>
		<slide id="452" showInTOC="" inSequence="" frameRate="30" totalFrames="30" usePptxSlideDur="0" lockInteractionSlide="false" isHiddenInteractionSl="false" isWrongInteractionSl="false" swfConvertorEngine="Nova" slideDuration="43.76" advance="auto" blockMovement="false" hideplaybar="false" type="normal">
			<content url="Slide38.swf" id="452"/>
			<backdrop displayBgSp="true"/>
			<master id="2" frameNum="0"/>
			<layout id="2" frameNum="0"/>
			<slidexml><AS3Class className="TL_50488494833944b29860fd45cd83ad2ayxy" classType="PptTmline_xyxyxyxyxyxyxyxyxyxyxyxyxyxy" frameRate="30" normalSlide="1"><OnLoadCallBacks/><Audios/></AS3Class></slidexml>
			<clickAnimations></clickAnimations>
			<webObjectContents/>
			<flvContents/>
			<audios id="40" duration=" 43760">
				<media url="a24x40.mp3" startMsecs="0" duration="43760" startAtMSecs="0"/>
			</audios>
			<playbackActions></playbackActions>
			<slideTitle>@@</slideTitle>
			<notes isHTML="true"></notes>
			<slideThumbnail url="thumb.swf" frame="39"/>
			<slideSpeaker index="4"/>
		</slide>
		<slide id="453" showInTOC="" inSequence="" frameRate="30" totalFrames="30" usePptxSlideDur="0" lockInteractionSlide="false" isHiddenInteractionSl="false" isWrongInteractionSl="false" swfConvertorEngine="Nova" slideDuration="27.93" advance="auto" blockMovement="false" hideplaybar="false" type="normal">
			<content url="Slide39.swf" id="453"/>
			<backdrop displayBgSp="true"/>
			<master id="2" frameNum="0"/>
			<layout id="2" frameNum="0"/>
			<slidexml><AS3Class className="TL_2dccc598112c46bba8c9006088a2f8e0yxy" classType="PptTmline_xyxyxyxyxyxyxyxyxyxyxyxyxyxy" frameRate="30" normalSlide="1"><OnLoadCallBacks/><Audios/></AS3Class></slidexml>
			<clickAnimations></clickAnimations>
			<webObjectContents/>
			<flvContents/>
			<audios id="41" duration=" 27930">
				<media url="a24x41.mp3" startMsecs="0" duration="27930" startAtMSecs="0"/>
			</audios>
			<playbackActions></playbackActions>
			<slideTitle>@@</slideTitle>
			<notes isHTML="true"></notes>
			<slideThumbnail url="thumb.swf" frame="40"/>
			<slideSpeaker index="4"/>
		</slide>
		<slide id="454" showInTOC="" inSequence="" frameRate="30" totalFrames="30" usePptxSlideDur="0" lockInteractionSlide="false" isHiddenInteractionSl="false" isWrongInteractionSl="false" swfConvertorEngine="Nova" slideDuration="52.01" advance="auto" blockMovement="false" hideplaybar="false" type="normal">
			<content url="Slide40.swf" id="454"/>
			<backdrop displayBgSp="true"/>
			<master id="2" frameNum="0"/>
			<layout id="2" frameNum="0"/>
			<slidexml><AS3Class className="TL_58c51aabd0b643a886367001523e1473yxy" classType="PptTmline_xyxyxyxyxyxyxyxyxyxyxyxyxyxy" frameRate="30" normalSlide="1"><OnLoadCallBacks/><Audios/></AS3Class></slidexml>
			<clickAnimations></clickAnimations>
			<webObjectContents/>
			<flvContents/>
			<audios id="42" duration=" 52010">
				<media url="a24x42.mp3" startMsecs="0" duration="52010" startAtMSecs="0"/>
			</audios>
			<playbackActions></playbackActions>
			<slideTitle>@@</slideTitle>
			<notes isHTML="true"></notes>
			<slideThumbnail url="thumb.swf" frame="41"/>
			<slideSpeaker index="4"/>
		</slide>
		<slide id="455" showInTOC="" inSequence="" frameRate="30" totalFrames="30" usePptxSlideDur="0" lockInteractionSlide="false" isHiddenInteractionSl="false" isWrongInteractionSl="false" swfConvertorEngine="Nova" slideDuration="49.73" advance="auto" blockMovement="false" hideplaybar="false" type="normal">
			<content url="Slide41.swf" id="455"/>
			<backdrop displayBgSp="true"/>
			<master id="2" frameNum="0"/>
			<layout id="2" frameNum="0"/>
			<slidexml><AS3Class className="TL_51454149f61a4887b30ca2df220d4e21yxy" classType="PptTmline_xyxyxyxyxyxyxyxyxyxyxyxyxyxy" frameRate="30" normalSlide="1"><OnLoadCallBacks/><Audios/></AS3Class></slidexml>
			<clickAnimations></clickAnimations>
			<webObjectContents/>
			<flvContents/>
			<audios id="43" duration=" 49730">
				<media url="a24x43.mp3" startMsecs="0" duration="49730" startAtMSecs="0"/>
			</audios>
			<playbackActions></playbackActions>
			<slideTitle>@@</slideTitle>
			<notes isHTML="true"></notes>
			<slideThumbnail url="thumb.swf" frame="42"/>
			<slideSpeaker index="4"/>
		</slide>
		<slide id="456" showInTOC="" inSequence="" frameRate="30" totalFrames="30" usePptxSlideDur="0" lockInteractionSlide="false" isHiddenInteractionSl="false" isWrongInteractionSl="false" swfConvertorEngine="Nova" slideDuration="40.11" advance="auto" blockMovement="false" hideplaybar="false" type="normal">
			<content url="Slide42.swf" id="456"/>
			<backdrop displayBgSp="true"/>
			<master id="2" frameNum="0"/>
			<layout id="2" frameNum="0"/>
			<slidexml><AS3Class className="TL_d69008d811f44eb4abde71038ef23b71yxy" classType="PptTmline_xyxyxyxyxyxyxyxyxyxyxyxyxyxy" frameRate="30" normalSlide="1"><OnLoadCallBacks/><Audios/></AS3Class></slidexml>
			<clickAnimations></clickAnimations>
			<webObjectContents/>
			<flvContents/>
			<audios id="44" duration=" 40110">
				<media url="a24x44.mp3" startMsecs="0" duration="40110" startAtMSecs="0"/>
			</audios>
			<playbackActions></playbackActions>
			<slideTitle>@@</slideTitle>
			<notes isHTML="true"></notes>
			<slideThumbnail url="thumb.swf" frame="43"/>
			<slideSpeaker index="4"/>
		</slide>
		<slide id="463" showInTOC="" inSequence="" frameRate="30" totalFrames="30" usePptxSlideDur="0" lockInteractionSlide="false" isHiddenInteractionSl="false" isWrongInteractionSl="false" swfConvertorEngine="Nova" slideDuration="35.55" advance="auto" blockMovement="false" hideplaybar="false" type="normal">
			<content url="Slide43.swf" id="463"/>
			<backdrop displayBgSp="true"/>
			<master id="2" frameNum="0"/>
			<layout id="2" frameNum="0"/>
			<slidexml><AS3Class className="TL_9ac271d3ae64484697647a96dd6e0e59yxy" classType="PptTmline_xyxyxyxyxyxyxyxyxyxyxyxyxyxy" frameRate="30" normalSlide="1"><OnLoadCallBacks/><Audios/></AS3Class></slidexml>
			<clickAnimations></clickAnimations>
			<webObjectContents/>
			<flvContents/>
			<audios id="45" duration=" 35550">
				<media url="a24x45.mp3" startMsecs="0" duration="35550" startAtMSecs="0"/>
			</audios>
			<playbackActions></playbackActions>
			<slideTitle>@@</slideTitle>
			<notes isHTML="true"></notes>
			<slideThumbnail url="thumb.swf" frame="44"/>
			<slideSpeaker index="4"/>
		</slide>
		<slide id="464" showInTOC="" inSequence="" frameRate="30" totalFrames="30" usePptxSlideDur="0" lockInteractionSlide="false" isHiddenInteractionSl="false" isWrongInteractionSl="false" swfConvertorEngine="Nova" slideDuration="48.26" advance="auto" blockMovement="false" hideplaybar="false" type="normal">
			<content url="Slide44.swf" id="464"/>
			<backdrop displayBgSp="true"/>
			<master id="2" frameNum="0"/>
			<layout id="2" frameNum="0"/>
			<slidexml><AS3Class className="TL_3f328bbc7d354a54b9b55d16075f1f2ayxy" classType="PptTmline_xyxyxyxyxyxyxyxyxyxyxyxyxyxy" frameRate="30" normalSlide="1"><OnLoadCallBacks/><Audios/></AS3Class></slidexml>
			<clickAnimations></clickAnimations>
			<webObjectContents/>
			<flvContents/>
			<audios id="46" duration=" 48260">
				<media url="a24x46.mp3" startMsecs="0" duration="48260" startAtMSecs="0"/>
			</audios>
			<playbackActions></playbackActions>
			<slideTitle>@@</slideTitle>
			<notes isHTML="true"></notes>
			<slideThumbnail url="thumb.swf" frame="45"/>
			<slideSpeaker index="4"/>
		</slide>
		<slide id="458" showInTOC="" inSequence="" frameRate="30" totalFrames="30" usePptxSlideDur="0" lockInteractionSlide="false" isHiddenInteractionSl="false" isWrongInteractionSl="false" swfConvertorEngine="Nova" slideDuration="28.52" advance="auto" blockMovement="false" hideplaybar="false" type="normal">
			<content url="Slide45.swf" id="458"/>
			<backdrop displayBgSp="true"/>
			<master id="2" frameNum="0"/>
			<layout id="2" frameNum="0"/>
			<slidexml><AS3Class className="TL_02be4ac824e4435b8c9a823235a2a681yxy" classType="PptTmline_xyxyxyxyxyxyxyxyxyxyxyxyxyxy" frameRate="30" normalSlide="1"><OnLoadCallBacks/><Audios/></AS3Class></slidexml>
			<clickAnimations></clickAnimations>
			<webObjectContents/>
			<flvContents/>
			<audios id="47" duration=" 28520">
				<media url="a24x47.mp3" startMsecs="0" duration="28520" startAtMSecs="0"/>
			</audios>
			<playbackActions></playbackActions>
			<slideTitle>@@</slideTitle>
			<notes isHTML="true"></notes>
			<slideThumbnail url="thumb.swf" frame="46"/>
			<slideSpeaker index="4"/>
		</slide>
		<slide id="459" showInTOC="" inSequence="" frameRate="30" totalFrames="30" usePptxSlideDur="0" lockInteractionSlide="false" isHiddenInteractionSl="false" isWrongInteractionSl="false" swfConvertorEngine="Nova" slideDuration="7.48" advance="auto" blockMovement="false" hideplaybar="false" type="normal">
			<content url="Slide46.swf" id="459"/>
			<backdrop displayBgSp="true"/>
			<master id="2" frameNum="0"/>
			<layout id="2" frameNum="0"/>
			<slidexml><AS3Class className="TL_1fc155b90e7b4d2d905dde99a503e5fcyxy" classType="PptTmline_xyxyxyxyxyxyxyxyxyxyxyxyxyxy" frameRate="30" normalSlide="1"><OnLoadCallBacks/><Audios/></AS3Class></slidexml>
			<clickAnimations></clickAnimations>
			<webObjectContents/>
			<flvContents/>
			<audios id="48" duration=" 7480">
				<media url="a24x48.mp3" startMsecs="0" duration="7480" startAtMSecs="0"/>
			</audios>
			<playbackActions></playbackActions>
			<slideTitle>@@</slideTitle>
			<notes isHTML="true"></notes>
			<slideThumbnail url="thumb.swf" frame="47"/>
			<slideSpeaker index="4"/>
		</slide>
		<slide id="403" showInTOC="" inSequence="" frameRate="30" totalFrames="30" usePptxSlideDur="0" lockInteractionSlide="false" isHiddenInteractionSl="false" isWrongInteractionSl="false" swfConvertorEngine="Nova" slideDuration="5" advance="auto" blockMovement="false" hideplaybar="false" type="normal">
			<content url="Slide47.swf" id="403"/>
			<backdrop displayBgSp="true"/>
			<master id="1" frameNum="0"/>
			<layout id="3" frameNum="0"/>
			<slidexml><AS3Class className="TL_0f2b9adf01bc4ab59b4bc5c32bdbad0ayxy" classType="PptTmline_xyxyxyxyxyxyxyxyxyxyxyxyxyxy" frameRate="30" normalSlide="1"><OnLoadCallBacks/><Audios/></AS3Class></slidexml>
			<clickAnimations></clickAnimations>
			<webObjectContents/>
			<flvContents/>
			<audios duration="5000"/>
			<playbackActions></playbackActions>
			<slideTitle>@Mentions légales@</slideTitle>
			<notes isHTML="true"></notes>
			<slideThumbnail url="thumb.swf" frame="48"/>
			<slideSpeaker index="4"/>
		</slide>
	</slides>
	<quizzes>
		<reportingOptions statusReportingOption="0" successReportingCriteria="-1" completionReportingCriteria="-1" slideViewCompletionCriteria="-1" slideViewSuccessCriteria="-1" quizCompletionCriteria="-1" quizSuccessCriteria="-1" completionCriteriaSlideViewVal="0" successCriteriaSlideViewVal="0" dataToReport="1" exitNormal="0" isTracked="false"></reportingOptions>
		<quizSettings showQuestionList="false" showScores="true" showPassScore="false" showCurrentScore="false" showQuestionMarks="false" showAttempts="true" showQuizAttempts="false" showQuestionAttempts="false" showQuestionCorrectFeedback="true" showQuestionIncorrectFeedback="true" showQuizNavigationWarning="true"></quizSettings>
	</quizzes>
	<attachments></attachments>
</presentation>
