<?xml version="1.0" encoding="utf-8"?>
<presentation width="960" height="540" isRTL="0" preview="0" enableAccessibility="NaN" defaultSlideDuration="5" start="play" slideTitleFormat="%n. %s" buildNum="11.0.0.133">
	<presentationTitle>Chapitre 2 : Vieillissement de l'Humain. Des théories.</presentationTitle>
	<speakers>
		<speaker>
			<name>Alain FRANCO</name>
			<speakerTitle>Professeur de médecine (Université Joseph Fourier - Grenoble)</speakerTitle>
			<image>spk10086.jpg</image>
		</speaker>
		<speaker>
			<name>Gaëtan GAVAZZI</name>
			<speakerTitle>Professeur CHU Grenoble (UGA)</speakerTitle>
			<image>spk10565.jpg</image>
		</speaker>
	</speakers>
	<search url="srchdata.xml"/>
	<presentationBg url="bg.swf"/>
	<masters><master url="Master0.swf" id="1" totalFrames="1"><backdrop frameNum="0"/><slidexml><AS3Class className="TL_295d9b26fb0549c3ae3335448e7ea151yxy" classType="PptTmline_xyxyxyxyxyxyxyxyxyxyxyxyxyxy" frameRate="30"><OnLoadCallBacks/><Audios/></AS3Class></slidexml></master><master url="Master1.swf" id="2" totalFrames="1"><backdrop frameNum="1"/><slidexml><AS3Class className="TL_b61b92db9ec64bea8867cda2f01d2ec1yxy" classType="PptTmline_xyxyxyxyxyxyxyxyxyxyxyxyxyxy" frameRate="30"><OnLoadCallBacks/><Audios/></AS3Class></slidexml></master></masters>
	<layouts><layout url="Layout0.swf" id="1" totalFrames="1"><backdrop displayBgSp="true"/><slidexml><AS3Class className="TL_261d2f27682d46f5b7f01b8b7c2cda67yxy" classType="PptTmline_xyxyxyxyxyxyxyxyxyxyxyxyxyxy" frameRate="30"><OnLoadCallBacks/><Audios/></AS3Class></slidexml></layout><layout url="Layout1.swf" id="2" totalFrames="1"><backdrop displayBgSp="true"/><slidexml><AS3Class className="TL_986d1c9afe6f421aa97a6e3a6b6b7bbfyxy" classType="PptTmline_xyxyxyxyxyxyxyxyxyxyxyxyxyxy" frameRate="30"><OnLoadCallBacks/><Audios/></AS3Class></slidexml></layout><layout url="Layout2.swf" id="3" totalFrames="1"><backdrop displayBgSp="true"/><slidexml><AS3Class className="TL_e128fbef39f14692afd2b2e9b6ca0429yxy" classType="PptTmline_xyxyxyxyxyxyxyxyxyxyxyxyxyxy" frameRate="30"><OnLoadCallBacks/><Audios/></AS3Class></slidexml></layout><layout url="Layout3.swf" id="4" totalFrames="1"><backdrop displayBgSp="true"/><slidexml><AS3Class className="TL_f9b9a4ccaee74b3d8d2ec8ec2d676e53yxy" classType="PptTmline_xyxyxyxyxyxyxyxyxyxyxyxyxyxy" frameRate="30"><OnLoadCallBacks/><Audios/></AS3Class></slidexml></layout><layout url="Layout4.swf" id="5" totalFrames="1"><backdrop displayBgSp="true"/><slidexml><AS3Class className="TL_4ebe8387138a44aabdb3eb68776ccd02yxy" classType="PptTmline_xyxyxyxyxyxyxyxyxyxyxyxyxyxy" frameRate="30"><OnLoadCallBacks/><Audios/></AS3Class></slidexml></layout></layouts>
	<slides>
		<slide id="258" showInTOC="" inSequence="" frameRate="30" totalFrames="30" usePptxSlideDur="0" lockInteractionSlide="false" isHiddenInteractionSl="false" isWrongInteractionSl="false" swfConvertorEngine="Nova" slideDuration="22.62" advance="auto" blockMovement="false" hideplaybar="false" type="normal">
			<transition/>
			<content url="Slide0.swf" id="258"/>
			<backdrop displayBgSp="true"/>
			<master id="1" frameNum="0"/>
			<layout id="1" frameNum="0"/>
			<slidexml><AS3Class className="TL_a75985ae3f414cfa9de43e20efee82d3yxy" classType="PptTmline_xyxyxyxyxyxyxyxyxyxyxyxyxyxy" frameRate="30" normalSlide="1"><OnLoadCallBacks/><Audios/></AS3Class></slidexml>
			<clickAnimations></clickAnimations>
			<webObjectContents/>
			<flvContents/>
			<audios id="1" duration=" 22620">
				<media url="a24x1.mp3" startMsecs="0" duration="22620" startAtMSecs="0"/>
			</audios>
			<playbackActions></playbackActions>
			<slideTitle>@Chapitre 2 :  Vieillissement de l’humain. Des théories@</slideTitle>
			<notes isHTML="true"></notes>
			<slideThumbnail url="thumb.swf" frame="1"/>
			<slideSpeaker index="1"/>
		</slide>
		<slide id="291" showInTOC="" inSequence="" frameRate="30" totalFrames="30" usePptxSlideDur="0" lockInteractionSlide="false" isHiddenInteractionSl="false" isWrongInteractionSl="false" swfConvertorEngine="Nova" slideDuration="36.74" advance="auto" blockMovement="false" hideplaybar="false" type="normal">
			<transition/>
			<content url="Slide1.swf" id="291"/>
			<backdrop displayBgSp="true"/>
			<master id="2" frameNum="0"/>
			<layout id="2" frameNum="0"/>
			<slidexml><AS3Class className="TL_15aface8ce2649bcb64bbce30a4451edyxy" classType="PptTmline_xyxyxyxyxyxyxyxyxyxyxyxyxyxy" frameRate="30" normalSlide="1"><OnLoadCallBacks/><Audios/></AS3Class></slidexml>
			<clickAnimations></clickAnimations>
			<webObjectContents/>
			<flvContents/>
			<audios id="2" duration=" 36740">
				<media url="a24x2.mp3" startMsecs="0" duration="36740" startAtMSecs="0"/>
			</audios>
			<playbackActions></playbackActions>
			<slideTitle>@@</slideTitle>
			<notes isHTML="true"></notes>
			<slideThumbnail url="thumb.swf" frame="2"/>
			<slideSpeaker index="1"/>
		</slide>
		<slide id="292" showInTOC="" inSequence="" frameRate="30" totalFrames="30" usePptxSlideDur="0" lockInteractionSlide="false" isHiddenInteractionSl="false" isWrongInteractionSl="false" swfConvertorEngine="Nova" slideDuration="57.84" advance="auto" blockMovement="false" hideplaybar="false" type="normal">
			<transition/>
			<content url="Slide2.swf" id="292"/>
			<backdrop displayBgSp="true"/>
			<master id="2" frameNum="0"/>
			<layout id="3" frameNum="0"/>
			<slidexml><AS3Class className="TL_c5f68b6cf4844ae3b4e06654ad08148eyxy" classType="PptTmline_xyxyxyxyxyxyxyxyxyxyxyxyxyxy" frameRate="30" normalSlide="1"><OnLoadCallBacks/><Audios/></AS3Class></slidexml>
			<clickAnimations></clickAnimations>
			<webObjectContents/>
			<flvContents/>
			<audios id="3" duration=" 57840">
				<media url="a24x3.mp3" startMsecs="0" duration="57840" startAtMSecs="0"/>
			</audios>
			<playbackActions></playbackActions>
			<slideTitle>@@</slideTitle>
			<notes isHTML="true"></notes>
			<slideThumbnail url="thumb.swf" frame="3"/>
			<slideSpeaker index="1"/>
		</slide>
		<slide id="293" showInTOC="" inSequence="" frameRate="30" totalFrames="30" usePptxSlideDur="0" lockInteractionSlide="false" isHiddenInteractionSl="false" isWrongInteractionSl="false" swfConvertorEngine="Nova" slideDuration="97.23" advance="auto" blockMovement="false" hideplaybar="false" type="normal">
			<transition/>
			<content url="Slide3.swf" id="293"/>
			<backdrop displayBgSp="true"/>
			<master id="2" frameNum="0"/>
			<layout id="2" frameNum="0"/>
			<slidexml><AS3Class className="TL_09e77b784dff4d6898b1e4dfcb9aa6bayxy" classType="PptTmline_xyxyxyxyxyxyxyxyxyxyxyxyxyxy" frameRate="30" normalSlide="1"><OnLoadCallBacks/><Audios/></AS3Class></slidexml>
			<clickAnimations></clickAnimations>
			<webObjectContents/>
			<flvContents/>
			<audios id="4" duration=" 97230">
				<media url="a24x4.mp3" startMsecs="0" duration="97230" startAtMSecs="0"/>
			</audios>
			<playbackActions></playbackActions>
			<slideTitle>@@</slideTitle>
			<notes isHTML="true"></notes>
			<slideThumbnail url="thumb.swf" frame="4"/>
			<slideSpeaker index="1"/>
		</slide>
		<slide id="294" showInTOC="" inSequence="" frameRate="30" totalFrames="30" usePptxSlideDur="0" lockInteractionSlide="false" isHiddenInteractionSl="false" isWrongInteractionSl="false" swfConvertorEngine="Nova" slideDuration="212.12" advance="auto" blockMovement="false" hideplaybar="false" type="normal">
			<transition/>
			<content url="Slide4.swf" id="294"/>
			<backdrop displayBgSp="true"/>
			<master id="2" frameNum="0"/>
			<layout id="2" frameNum="0"/>
			<slidexml><AS3Class className="TL_f4b5e25d1f244913b80a7d80dd571b50yxy" classType="PptTmline_xyxyxyxyxyxyxyxyxyxyxyxyxyxy" frameRate="30" normalSlide="1"><OnLoadCallBacks/><Audios/></AS3Class></slidexml>
			<clickAnimations></clickAnimations>
			<webObjectContents/>
			<flvContents/>
			<audios id="5" duration=" 212120">
				<media url="a24x5.mp3" startMsecs="0" duration="212120" startAtMSecs="0"/>
			</audios>
			<playbackActions></playbackActions>
			<slideTitle>@@</slideTitle>
			<notes isHTML="true"></notes>
			<slideThumbnail url="thumb.swf" frame="5"/>
			<slideSpeaker index="1"/>
		</slide>
		<slide id="295" showInTOC="" inSequence="" frameRate="30" totalFrames="30" usePptxSlideDur="0" lockInteractionSlide="false" isHiddenInteractionSl="false" isWrongInteractionSl="false" swfConvertorEngine="Nova" slideDuration="66.04" advance="auto" blockMovement="false" hideplaybar="false" type="normal">
			<transition/>
			<content url="Slide5.swf" id="295"/>
			<backdrop displayBgSp="true"/>
			<master id="2" frameNum="0"/>
			<layout id="3" frameNum="0"/>
			<slidexml><AS3Class className="TL_88717915bd384e3d9fcd5e1f191132a1yxy" classType="PptTmline_xyxyxyxyxyxyxyxyxyxyxyxyxyxy" frameRate="30" normalSlide="1"><OnLoadCallBacks/><Audios/></AS3Class></slidexml>
			<clickAnimations></clickAnimations>
			<webObjectContents/>
			<flvContents/>
			<audios id="6" duration=" 66040">
				<media url="a24x6.mp3" startMsecs="0" duration="66040" startAtMSecs="0"/>
			</audios>
			<playbackActions></playbackActions>
			<slideTitle>@Attributs du vieillissement@</slideTitle>
			<notes isHTML="true"></notes>
			<slideThumbnail url="thumb.swf" frame="6"/>
			<slideSpeaker index="1"/>
		</slide>
		<slide id="296" showInTOC="" inSequence="" frameRate="30" totalFrames="30" usePptxSlideDur="0" lockInteractionSlide="false" isHiddenInteractionSl="false" isWrongInteractionSl="false" swfConvertorEngine="Nova" slideDuration="22.82" advance="auto" blockMovement="false" hideplaybar="false" type="normal">
			<transition/>
			<content url="Slide6.swf" id="296"/>
			<backdrop displayBgSp="true"/>
			<master id="2" frameNum="0"/>
			<layout id="2" frameNum="0"/>
			<slidexml><AS3Class className="TL_78428007a4aa434b85389de4fce392a8yxy" classType="PptTmline_xyxyxyxyxyxyxyxyxyxyxyxyxyxy" frameRate="30" normalSlide="1"><OnLoadCallBacks/><Audios/></AS3Class></slidexml>
			<clickAnimations></clickAnimations>
			<webObjectContents/>
			<flvContents/>
			<audios id="7" duration=" 22820">
				<media url="a24x7.mp3" startMsecs="0" duration="22820" startAtMSecs="0"/>
			</audios>
			<playbackActions></playbackActions>
			<slideTitle>@@</slideTitle>
			<notes isHTML="true"></notes>
			<slideThumbnail url="thumb.swf" frame="7"/>
			<slideSpeaker index="1"/>
		</slide>
		<slide id="297" showInTOC="" inSequence="" frameRate="30" totalFrames="30" usePptxSlideDur="0" lockInteractionSlide="false" isHiddenInteractionSl="false" isWrongInteractionSl="false" swfConvertorEngine="Nova" slideDuration="145.44" advance="auto" blockMovement="false" hideplaybar="false" type="normal">
			<transition/>
			<content url="Slide7.swf" id="297"/>
			<backdrop displayBgSp="true"/>
			<master id="2" frameNum="0"/>
			<layout id="4" frameNum="0"/>
			<slidexml><AS3Class className="TL_96e996c8f2174dcf9c44a9b6c785f24ayxy" classType="PptTmline_xyxyxyxyxyxyxyxyxyxyxyxyxyxy" frameRate="30" normalSlide="1"><OnLoadCallBacks/><Audios/></AS3Class></slidexml>
			<clickAnimations></clickAnimations>
			<webObjectContents/>
			<flvContents/>
			<audios id="8" duration=" 145440">
				<media url="a24x8.mp3" startMsecs="0" duration="145440" startAtMSecs="0"/>
			</audios>
			<playbackActions></playbackActions>
			<slideTitle>@@</slideTitle>
			<notes isHTML="true"></notes>
			<slideThumbnail url="thumb.swf" frame="8"/>
			<slideSpeaker index="1"/>
		</slide>
		<slide id="298" showInTOC="" inSequence="" frameRate="30" totalFrames="30" usePptxSlideDur="0" lockInteractionSlide="false" isHiddenInteractionSl="false" isWrongInteractionSl="false" swfConvertorEngine="Nova" slideDuration="60.86" advance="auto" blockMovement="false" hideplaybar="false" type="normal">
			<transition/>
			<content url="Slide8.swf" id="298"/>
			<backdrop displayBgSp="true"/>
			<master id="2" frameNum="0"/>
			<layout id="4" frameNum="0"/>
			<slidexml><AS3Class className="TL_f28b99427f57462b8c6b87d489fb9c2ayxy" classType="PptTmline_xyxyxyxyxyxyxyxyxyxyxyxyxyxy" frameRate="30" normalSlide="1"><OnLoadCallBacks/><Audios/></AS3Class></slidexml>
			<clickAnimations></clickAnimations>
			<webObjectContents/>
			<flvContents/>
			<audios id="9" duration=" 60860">
				<media url="a24x9.mp3" startMsecs="0" duration="60860" startAtMSecs="0"/>
			</audios>
			<playbackActions></playbackActions>
			<slideTitle>@@</slideTitle>
			<notes isHTML="true"></notes>
			<slideThumbnail url="thumb.swf" frame="9"/>
			<slideSpeaker index="1"/>
		</slide>
		<slide id="299" showInTOC="" inSequence="" frameRate="30" totalFrames="30" usePptxSlideDur="0" lockInteractionSlide="false" isHiddenInteractionSl="false" isWrongInteractionSl="false" swfConvertorEngine="Nova" slideDuration="55.5" advance="auto" blockMovement="false" hideplaybar="false" type="normal">
			<transition/>
			<content url="Slide9.swf" id="299"/>
			<backdrop displayBgSp="true"/>
			<master id="2" frameNum="0"/>
			<layout id="4" frameNum="0"/>
			<slidexml><AS3Class className="TL_08b1b7bc719f424c802fb008c47335deyxy" classType="PptTmline_xyxyxyxyxyxyxyxyxyxyxyxyxyxy" frameRate="30" normalSlide="1"><OnLoadCallBacks/><Audios/></AS3Class></slidexml>
			<clickAnimations></clickAnimations>
			<webObjectContents/>
			<flvContents/>
			<audios id="10" duration=" 55500">
				<media url="a24x10.mp3" startMsecs="0" duration="55500" startAtMSecs="0"/>
			</audios>
			<playbackActions></playbackActions>
			<slideTitle>@@</slideTitle>
			<notes isHTML="true"></notes>
			<slideThumbnail url="thumb.swf" frame="10"/>
			<slideSpeaker index="1"/>
		</slide>
		<slide id="300" showInTOC="" inSequence="" frameRate="30" totalFrames="30" usePptxSlideDur="0" lockInteractionSlide="false" isHiddenInteractionSl="false" isWrongInteractionSl="false" swfConvertorEngine="Nova" slideDuration="5" advance="auto" blockMovement="false" hideplaybar="false" type="normal">
			<transition/>
			<content url="Slide10.swf" id="300"/>
			<backdrop displayBgSp="true"/>
			<master id="2" frameNum="0"/>
			<layout id="3" frameNum="0"/>
			<slidexml><AS3Class className="TL_0b4ccc489f5b40e4845be6edbad9bf87yxy" classType="PptTmline_xyxyxyxyxyxyxyxyxyxyxyxyxyxy" frameRate="30" normalSlide="1"><OnLoadCallBacks/><Audios/></AS3Class></slidexml>
			<clickAnimations></clickAnimations>
			<webObjectContents/>
			<flvContents/>
			<audios duration="5000"/>
			<playbackActions></playbackActions>
			<slideTitle>@Les Théories du vieillissement biologiques@</slideTitle>
			<notes isHTML="true"></notes>
			<slideThumbnail url="thumb.swf" frame="11"/>
			<slideSpeaker index="1"/>
		</slide>
		<slide id="301" showInTOC="" inSequence="" frameRate="30" totalFrames="30" usePptxSlideDur="0" lockInteractionSlide="false" isHiddenInteractionSl="false" isWrongInteractionSl="false" swfConvertorEngine="Nova" slideDuration="110.08" advance="auto" blockMovement="false" hideplaybar="false" type="normal">
			<transition/>
			<content url="Slide11.swf" id="301"/>
			<backdrop displayBgSp="true"/>
			<master id="2" frameNum="0"/>
			<layout id="3" frameNum="0"/>
			<slidexml><AS3Class className="TL_310a004a0c644ff5af98cf7fd5b2da20yxy" classType="PptTmline_xyxyxyxyxyxyxyxyxyxyxyxyxyxy" frameRate="30" normalSlide="1"><OnLoadCallBacks/><Audios/></AS3Class></slidexml>
			<clickAnimations></clickAnimations>
			<webObjectContents/>
			<flvContents/>
			<audios id="12" duration=" 110080">
				<media url="a24x12.mp3" startMsecs="0" duration="110080" startAtMSecs="0"/>
			</audios>
			<playbackActions></playbackActions>
			<slideTitle>@Théories du Vieillissement biologique  @</slideTitle>
			<notes isHTML="true"></notes>
			<slideThumbnail url="thumb.swf" frame="12"/>
			<slideSpeaker index="1"/>
		</slide>
		<slide id="302" showInTOC="" inSequence="" frameRate="30" totalFrames="30" usePptxSlideDur="0" lockInteractionSlide="false" isHiddenInteractionSl="false" isWrongInteractionSl="false" swfConvertorEngine="Nova" slideDuration="56.88" advance="auto" blockMovement="false" hideplaybar="false" type="normal">
			<transition/>
			<content url="Slide12.swf" id="302"/>
			<backdrop displayBgSp="true"/>
			<master id="2" frameNum="0"/>
			<layout id="3" frameNum="0"/>
			<slidexml><AS3Class className="TL_50c1b9ae65fb40e3a7b96d53525e0c3byxy" classType="PptTmline_xyxyxyxyxyxyxyxyxyxyxyxyxyxy" frameRate="30" normalSlide="1"><OnLoadCallBacks/><Audios/></AS3Class></slidexml>
			<clickAnimations></clickAnimations>
			<webObjectContents/>
			<flvContents/>
			<audios id="13" duration=" 56880">
				<media url="a24x13.mp3" startMsecs="0" duration="56880" startAtMSecs="0"/>
			</audios>
			<playbackActions></playbackActions>
			<slideTitle>@Théories du Vieillissement biologique  @</slideTitle>
			<notes isHTML="true"></notes>
			<slideThumbnail url="thumb.swf" frame="13"/>
			<slideSpeaker index="1"/>
		</slide>
		<slide id="303" showInTOC="" inSequence="" frameRate="30" totalFrames="30" usePptxSlideDur="0" lockInteractionSlide="false" isHiddenInteractionSl="false" isWrongInteractionSl="false" swfConvertorEngine="Nova" slideDuration="85.58" advance="auto" blockMovement="false" hideplaybar="false" type="normal">
			<transition/>
			<content url="Slide13.swf" id="303"/>
			<backdrop displayBgSp="true"/>
			<master id="2" frameNum="0"/>
			<layout id="3" frameNum="0"/>
			<slidexml><AS3Class className="TL_8b513b6b10554bd0b39f1e2ab3abc6ebyxy" classType="PptTmline_xyxyxyxyxyxyxyxyxyxyxyxyxyxy" frameRate="30" normalSlide="1"><OnLoadCallBacks/><Audios/></AS3Class></slidexml>
			<clickAnimations></clickAnimations>
			<webObjectContents/>
			<flvContents/>
			<audios id="14" duration=" 85580">
				<media url="a24x14.mp3" startMsecs="0" duration="85580" startAtMSecs="0"/>
			</audios>
			<playbackActions></playbackActions>
			<slideTitle>@Les théories du Vieillissement biologique  @</slideTitle>
			<notes isHTML="true"></notes>
			<slideThumbnail url="thumb.swf" frame="14"/>
			<slideSpeaker index="1"/>
		</slide>
		<slide id="304" showInTOC="" inSequence="" frameRate="30" totalFrames="30" usePptxSlideDur="0" lockInteractionSlide="false" isHiddenInteractionSl="false" isWrongInteractionSl="false" swfConvertorEngine="Nova" slideDuration="90.39" advance="auto" blockMovement="false" hideplaybar="false" type="normal">
			<transition/>
			<content url="Slide14.swf" id="304"/>
			<backdrop displayBgSp="true"/>
			<master id="2" frameNum="0"/>
			<layout id="4" frameNum="0"/>
			<slidexml><AS3Class className="TL_8ed54b6ce28d4d07a943597bf4b7671byxy" classType="PptTmline_xyxyxyxyxyxyxyxyxyxyxyxyxyxy" frameRate="30" normalSlide="1"><OnLoadCallBacks/><Audios/></AS3Class></slidexml>
			<clickAnimations></clickAnimations>
			<webObjectContents/>
			<flvContents/>
			<audios id="15" duration=" 90390">
				<media url="a24x15.mp3" startMsecs="0" duration="90390" startAtMSecs="0"/>
			</audios>
			<playbackActions></playbackActions>
			<slideTitle>@@</slideTitle>
			<notes isHTML="true"></notes>
			<slideThumbnail url="thumb.swf" frame="15"/>
			<slideSpeaker index="1"/>
		</slide>
		<slide id="305" showInTOC="" inSequence="" frameRate="30" totalFrames="30" usePptxSlideDur="0" lockInteractionSlide="false" isHiddenInteractionSl="false" isWrongInteractionSl="false" swfConvertorEngine="Nova" slideDuration="147.13" advance="auto" blockMovement="false" hideplaybar="false" type="normal">
			<transition/>
			<content url="Slide15.swf" id="305"/>
			<backdrop displayBgSp="true"/>
			<master id="2" frameNum="0"/>
			<layout id="4" frameNum="0"/>
			<slidexml><AS3Class className="TL_2a8ad386ce644cc8a4cd8d121936e61fyxy" classType="PptTmline_xyxyxyxyxyxyxyxyxyxyxyxyxyxy" frameRate="30" normalSlide="1"><OnLoadCallBacks/><Audios/></AS3Class></slidexml>
			<clickAnimations></clickAnimations>
			<webObjectContents/>
			<flvContents/>
			<audios id="16" duration=" 147130">
				<media url="a24x16.mp3" startMsecs="0" duration="147130" startAtMSecs="0"/>
			</audios>
			<playbackActions></playbackActions>
			<slideTitle>@Les théories non génétiques@</slideTitle>
			<notes isHTML="true"></notes>
			<slideThumbnail url="thumb.swf" frame="16"/>
			<slideSpeaker index="1"/>
		</slide>
		<slide id="307" showInTOC="" inSequence="" frameRate="30" totalFrames="30" usePptxSlideDur="0" lockInteractionSlide="false" isHiddenInteractionSl="false" isWrongInteractionSl="false" swfConvertorEngine="Nova" slideDuration="121.39" advance="auto" blockMovement="false" hideplaybar="false" type="normal">
			<transition/>
			<content url="Slide16.swf" id="307"/>
			<backdrop displayBgSp="true"/>
			<master id="2" frameNum="0"/>
			<layout id="4" frameNum="0"/>
			<slidexml><AS3Class className="TL_5936094bc99b43b981509f03e553eaf0yxy" classType="PptTmline_xyxyxyxyxyxyxyxyxyxyxyxyxyxy" frameRate="30" normalSlide="1"><OnLoadCallBacks/><Audios/></AS3Class></slidexml>
			<clickAnimations></clickAnimations>
			<webObjectContents/>
			<flvContents/>
			<audios id="18" duration=" 121390">
				<media url="a24x18.mp3" startMsecs="0" duration="121390" startAtMSecs="0"/>
			</audios>
			<playbackActions></playbackActions>
			<slideTitle>@@</slideTitle>
			<notes isHTML="true">&lt;TextFlow xmlns = "http://ns.adobe.com/textLayout/2008" fontFamily = "Verdana" fontSize = "9"&gt;&lt;p&gt;&lt;span &gt;Il s&lt;/span&gt;&lt;span &gt;’&lt;/span&gt;&lt;span &gt;agit de la réaction oxydative ( stress oxydant est aussi appel , stress lié au Espèce réactive de l&lt;/span&gt;&lt;span &gt;’&lt;/span&gt;&lt;span &gt;oxygène ou radicaux libres) … &lt;/span&gt;&lt;span &gt;&lt;br/&gt;&lt;/span&gt;&lt;span &gt;Radicaux libres et télomères, raccourcissement des télomères,&lt;/span&gt;&lt;span &gt;&lt;br/&gt;&lt;/span&gt;&lt;span &gt;Et Rôles  multiples&lt;/span&gt;&lt;span &gt;&lt;br/&gt;&lt;/span&gt;&lt;span &gt;	De modification de transduction du signal&lt;/span&gt;&lt;span &gt;&lt;br/&gt;&lt;/span&gt;&lt;span &gt;	D&lt;/span&gt;&lt;span &gt;’&lt;/span&gt;&lt;span &gt;altération protéique, lipidique ou de l&lt;/span&gt;&lt;span &gt;’&lt;/span&gt;&lt;span &gt;ADN.&lt;/span&gt;&lt;span &gt;&lt;br/&gt;&lt;/span&gt;&lt;span &gt;	glycation protéique&lt;/span&gt;&lt;span &gt;&lt;br/&gt;&lt;/span&gt;&lt;/p&gt;&lt;/TextFlow&gt;</notes>
			<slideThumbnail url="thumb.swf" frame="17"/>
			<slideSpeaker index="1"/>
		</slide>
		<slide id="308" showInTOC="" inSequence="" frameRate="30" totalFrames="30" usePptxSlideDur="0" lockInteractionSlide="false" isHiddenInteractionSl="false" isWrongInteractionSl="false" swfConvertorEngine="Nova" slideDuration="51.67" advance="auto" blockMovement="false" hideplaybar="false" type="normal">
			<transition/>
			<content url="Slide17.swf" id="308"/>
			<backdrop displayBgSp="true"/>
			<master id="2" frameNum="0"/>
			<layout id="4" frameNum="0"/>
			<slidexml><AS3Class className="TL_4411945a6dcd4d0e8ffa84ca6a7f5d3eyxy" classType="PptTmline_xyxyxyxyxyxyxyxyxyxyxyxyxyxy" frameRate="30" normalSlide="1"><OnLoadCallBacks/><Audios/></AS3Class></slidexml>
			<clickAnimations></clickAnimations>
			<webObjectContents/>
			<flvContents/>
			<audios id="19" duration=" 51670">
				<media url="a24x19.mp3" startMsecs="0" duration="51670" startAtMSecs="0"/>
			</audios>
			<playbackActions></playbackActions>
			<slideTitle>@@</slideTitle>
			<notes isHTML="true"></notes>
			<slideThumbnail url="thumb.swf" frame="18"/>
			<slideSpeaker index="1"/>
		</slide>
		<slide id="306" showInTOC="" inSequence="" frameRate="30" totalFrames="30" usePptxSlideDur="0" lockInteractionSlide="false" isHiddenInteractionSl="false" isWrongInteractionSl="false" swfConvertorEngine="Nova" slideDuration="51.76" advance="auto" blockMovement="false" hideplaybar="false" type="normal">
			<transition/>
			<content url="Slide18.swf" id="306"/>
			<backdrop displayBgSp="true"/>
			<master id="2" frameNum="0"/>
			<layout id="4" frameNum="0"/>
			<slidexml><AS3Class className="TL_8751ab4eb687413697d95e627dc18738yxy" classType="PptTmline_xyxyxyxyxyxyxyxyxyxyxyxyxyxy" frameRate="30" normalSlide="1"><OnLoadCallBacks/><Audios/></AS3Class></slidexml>
			<clickAnimations></clickAnimations>
			<webObjectContents/>
			<flvContents/>
			<audios id="17" duration=" 51760">
				<media url="a24x17.mp3" startMsecs="0" duration="51760" startAtMSecs="0"/>
			</audios>
			<playbackActions></playbackActions>
			<slideTitle>@@</slideTitle>
			<notes isHTML="true"></notes>
			<slideThumbnail url="thumb.swf" frame="19"/>
			<slideSpeaker index="1"/>
		</slide>
		<slide id="311" showInTOC="" inSequence="" frameRate="30" totalFrames="30" usePptxSlideDur="0" lockInteractionSlide="false" isHiddenInteractionSl="false" isWrongInteractionSl="false" swfConvertorEngine="Nova" slideDuration="97.56" advance="auto" blockMovement="false" hideplaybar="false" type="normal">
			<transition/>
			<content url="Slide19.swf" id="311"/>
			<backdrop displayBgSp="true"/>
			<master id="2" frameNum="0"/>
			<layout id="4" frameNum="0"/>
			<slidexml><AS3Class className="TL_baffd138178c4627b2262eb0f061b7a4yxy" classType="PptTmline_xyxyxyxyxyxyxyxyxyxyxyxyxyxy" frameRate="30" normalSlide="1"><OnLoadCallBacks/><Audios/></AS3Class></slidexml>
			<clickAnimations></clickAnimations>
			<webObjectContents/>
			<flvContents/>
			<audios id="20" duration=" 97560">
				<media url="a24x20.mp3" startMsecs="0" duration="97560" startAtMSecs="0"/>
			</audios>
			<playbackActions></playbackActions>
			<slideTitle>@Les théories mixtes@</slideTitle>
			<notes isHTML="true"></notes>
			<slideThumbnail url="thumb.swf" frame="20"/>
			<slideSpeaker index="1"/>
		</slide>
		<slide id="310" showInTOC="" inSequence="" frameRate="30" totalFrames="30" usePptxSlideDur="0" lockInteractionSlide="false" isHiddenInteractionSl="false" isWrongInteractionSl="false" swfConvertorEngine="Nova" slideDuration="34.98" advance="auto" blockMovement="false" hideplaybar="false" type="normal">
			<transition/>
			<content url="Slide20.swf" id="310"/>
			<backdrop displayBgSp="true"/>
			<master id="2" frameNum="0"/>
			<layout id="4" frameNum="0"/>
			<slidexml><AS3Class className="TL_918bc56fa38243408740ab46de88c77cyxy" classType="PptTmline_xyxyxyxyxyxyxyxyxyxyxyxyxyxy" frameRate="30" normalSlide="1"><OnLoadCallBacks/><Audios/></AS3Class></slidexml>
			<clickAnimations></clickAnimations>
			<webObjectContents/>
			<flvContents/>
			<audios id="21" duration=" 34980">
				<media url="a24x21.mp3" startMsecs="0" duration="34980" startAtMSecs="0"/>
			</audios>
			<playbackActions></playbackActions>
			<slideTitle>@Les théories mixtes@</slideTitle>
			<notes isHTML="true"></notes>
			<slideThumbnail url="thumb.swf" frame="21"/>
			<slideSpeaker index="1"/>
		</slide>
		<slide id="312" showInTOC="" inSequence="" frameRate="30" totalFrames="30" usePptxSlideDur="0" lockInteractionSlide="false" isHiddenInteractionSl="false" isWrongInteractionSl="false" swfConvertorEngine="Nova" slideDuration="68.53" advance="auto" blockMovement="false" hideplaybar="false" type="normal">
			<transition/>
			<content url="Slide21.swf" id="312"/>
			<backdrop displayBgSp="true"/>
			<master id="2" frameNum="0"/>
			<layout id="4" frameNum="0"/>
			<slidexml><AS3Class className="TL_9c5bd5a19a9d4ab09efb343fe12579beyxy" classType="PptTmline_xyxyxyxyxyxyxyxyxyxyxyxyxyxy" frameRate="30" normalSlide="1"><OnLoadCallBacks/><Audios/></AS3Class></slidexml>
			<clickAnimations></clickAnimations>
			<webObjectContents/>
			<flvContents/>
			<audios id="22" duration=" 68530">
				<media url="a24x22.mp3" startMsecs="0" duration="68530" startAtMSecs="0"/>
			</audios>
			<playbackActions></playbackActions>
			<slideTitle>@Les théories mixtes@</slideTitle>
			<notes isHTML="true"></notes>
			<slideThumbnail url="thumb.swf" frame="22"/>
			<slideSpeaker index="1"/>
		</slide>
		<slide id="313" showInTOC="" inSequence="" frameRate="30" totalFrames="30" usePptxSlideDur="0" lockInteractionSlide="false" isHiddenInteractionSl="false" isWrongInteractionSl="false" swfConvertorEngine="Nova" slideDuration="47.54" advance="auto" blockMovement="false" hideplaybar="false" type="normal">
			<transition/>
			<content url="Slide22.swf" id="313"/>
			<backdrop displayBgSp="true"/>
			<master id="2" frameNum="0"/>
			<layout id="4" frameNum="0"/>
			<slidexml><AS3Class className="TL_8d19cdce680b454fb020748394b5aa5dyxy" classType="PptTmline_xyxyxyxyxyxyxyxyxyxyxyxyxyxy" frameRate="30" normalSlide="1"><OnLoadCallBacks/><Audios/></AS3Class></slidexml>
			<clickAnimations></clickAnimations>
			<webObjectContents/>
			<flvContents/>
			<audios id="23" duration=" 47540">
				<media url="a24x23.mp3" startMsecs="0" duration="47540" startAtMSecs="0"/>
			</audios>
			<playbackActions></playbackActions>
			<slideTitle>@@</slideTitle>
			<notes isHTML="true"></notes>
			<slideThumbnail url="thumb.swf" frame="23"/>
			<slideSpeaker index="1"/>
		</slide>
		<slide id="314" showInTOC="" inSequence="" frameRate="30" totalFrames="30" usePptxSlideDur="0" lockInteractionSlide="false" isHiddenInteractionSl="false" isWrongInteractionSl="false" swfConvertorEngine="Nova" slideDuration="96.76" advance="auto" blockMovement="false" hideplaybar="false" type="normal">
			<transition/>
			<content url="Slide23.swf" id="314"/>
			<backdrop displayBgSp="true"/>
			<master id="2" frameNum="0"/>
			<layout id="4" frameNum="0"/>
			<slidexml><AS3Class className="TL_7828ca35726040c1b06320635f86fdb3yxy" classType="PptTmline_xyxyxyxyxyxyxyxyxyxyxyxyxyxy" frameRate="30" normalSlide="1"><OnLoadCallBacks/><Audios/></AS3Class></slidexml>
			<clickAnimations></clickAnimations>
			<webObjectContents/>
			<flvContents/>
			<audios id="24" duration=" 96760">
				<media url="a24x24.mp3" startMsecs="0" duration="96760" startAtMSecs="0"/>
			</audios>
			<playbackActions></playbackActions>
			<slideTitle>@Performance fonctionnel d’un organe@</slideTitle>
			<notes isHTML="true"></notes>
			<slideThumbnail url="thumb.swf" frame="24"/>
			<slideSpeaker index="1"/>
		</slide>
		<slide id="315" showInTOC="" inSequence="" frameRate="30" totalFrames="30" usePptxSlideDur="0" lockInteractionSlide="false" isHiddenInteractionSl="false" isWrongInteractionSl="false" swfConvertorEngine="Nova" slideDuration="86.51" advance="auto" blockMovement="false" hideplaybar="false" type="normal">
			<transition/>
			<content url="Slide24.swf" id="315"/>
			<backdrop displayBgSp="true"/>
			<master id="2" frameNum="0"/>
			<layout id="4" frameNum="0"/>
			<slidexml><AS3Class className="TL_2c970e0a07584081b9df9b91641db163yxy" classType="PptTmline_xyxyxyxyxyxyxyxyxyxyxyxyxyxy" frameRate="30" normalSlide="1"><OnLoadCallBacks/><Audios/></AS3Class></slidexml>
			<clickAnimations></clickAnimations>
			<webObjectContents/>
			<flvContents/>
			<audios id="25" duration=" 86510">
				<media url="a24x25.mp3" startMsecs="0" duration="86510" startAtMSecs="0"/>
			</audios>
			<playbackActions></playbackActions>
			<slideTitle>@@</slideTitle>
			<notes isHTML="true"></notes>
			<slideThumbnail url="thumb.swf" frame="25"/>
			<slideSpeaker index="1"/>
		</slide>
		<slide id="316" showInTOC="" inSequence="" frameRate="30" totalFrames="30" usePptxSlideDur="0" lockInteractionSlide="false" isHiddenInteractionSl="false" isWrongInteractionSl="false" swfConvertorEngine="Nova" slideDuration="81.94" advance="auto" blockMovement="false" hideplaybar="false" type="normal">
			<transition/>
			<content url="Slide25.swf" id="316"/>
			<backdrop displayBgSp="true"/>
			<master id="2" frameNum="0"/>
			<layout id="4" frameNum="0"/>
			<slidexml><AS3Class className="TL_e99f3b3449c643b3b9a9244eb82a18f6yxy" classType="PptTmline_xyxyxyxyxyxyxyxyxyxyxyxyxyxy" frameRate="30" normalSlide="1"><OnLoadCallBacks/><Audios/></AS3Class></slidexml>
			<clickAnimations></clickAnimations>
			<webObjectContents/>
			<flvContents/>
			<audios id="26" duration=" 81940">
				<media url="a24x26.mp3" startMsecs="0" duration="81940" startAtMSecs="0"/>
			</audios>
			<playbackActions></playbackActions>
			<slideTitle>@@</slideTitle>
			<notes isHTML="true"></notes>
			<slideThumbnail url="thumb.swf" frame="26"/>
			<slideSpeaker index="1"/>
		</slide>
		<slide id="317" showInTOC="" inSequence="" frameRate="30" totalFrames="30" usePptxSlideDur="0" lockInteractionSlide="false" isHiddenInteractionSl="false" isWrongInteractionSl="false" swfConvertorEngine="Nova" slideDuration="78.21" advance="auto" blockMovement="false" hideplaybar="false" type="normal">
			<transition/>
			<content url="Slide26.swf" id="317"/>
			<backdrop displayBgSp="true"/>
			<master id="2" frameNum="0"/>
			<layout id="4" frameNum="0"/>
			<slidexml><AS3Class className="TL_e4057fd694da4e6bbe6b7df50f262dafyxy" classType="PptTmline_xyxyxyxyxyxyxyxyxyxyxyxyxyxy" frameRate="30" normalSlide="1"><OnLoadCallBacks/><Audios/></AS3Class></slidexml>
			<clickAnimations></clickAnimations>
			<webObjectContents/>
			<flvContents/>
			<audios id="27" duration=" 78210">
				<media url="a24x27.mp3" startMsecs="0" duration="78210" startAtMSecs="0"/>
			</audios>
			<playbackActions></playbackActions>
			<slideTitle>@@</slideTitle>
			<notes isHTML="true"></notes>
			<slideThumbnail url="thumb.swf" frame="27"/>
			<slideSpeaker index="1"/>
		</slide>
		<slide id="318" showInTOC="" inSequence="" frameRate="30" totalFrames="30" usePptxSlideDur="0" lockInteractionSlide="false" isHiddenInteractionSl="false" isWrongInteractionSl="false" swfConvertorEngine="Nova" slideDuration="82.92" advance="auto" blockMovement="false" hideplaybar="false" type="normal">
			<transition/>
			<content url="Slide27.swf" id="318"/>
			<backdrop displayBgSp="true"/>
			<master id="2" frameNum="0"/>
			<layout id="4" frameNum="0"/>
			<slidexml><AS3Class className="TL_f338c2ba75bc4df88e79be23a4120624yxy" classType="PptTmline_xyxyxyxyxyxyxyxyxyxyxyxyxyxy" frameRate="30" normalSlide="1"><OnLoadCallBacks/><Audios/></AS3Class></slidexml>
			<clickAnimations></clickAnimations>
			<webObjectContents/>
			<flvContents/>
			<audios id="28" duration=" 82920">
				<media url="a24x28.mp3" startMsecs="0" duration="82920" startAtMSecs="0"/>
			</audios>
			<playbackActions></playbackActions>
			<slideTitle>@@</slideTitle>
			<notes isHTML="true"></notes>
			<slideThumbnail url="thumb.swf" frame="28"/>
			<slideSpeaker index="1"/>
		</slide>
		<slide id="319" showInTOC="" inSequence="" frameRate="30" totalFrames="30" usePptxSlideDur="0" lockInteractionSlide="false" isHiddenInteractionSl="false" isWrongInteractionSl="false" swfConvertorEngine="Nova" slideDuration="5" advance="auto" blockMovement="false" hideplaybar="false" type="normal">
			<transition/>
			<content url="Slide28.swf" id="319"/>
			<backdrop displayBgSp="true"/>
			<master id="2" frameNum="0"/>
			<layout id="4" frameNum="0"/>
			<slidexml><AS3Class className="TL_0856b5132bd74160ae7f4aa2b853dc20yxy" classType="PptTmline_xyxyxyxyxyxyxyxyxyxyxyxyxyxy" frameRate="30" normalSlide="1"><OnLoadCallBacks/><Audios/></AS3Class></slidexml>
			<clickAnimations></clickAnimations>
			<webObjectContents/>
			<flvContents/>
			<audios duration="5000"/>
			<playbackActions></playbackActions>
			<slideTitle>@Des interventions anti-vieillissement@</slideTitle>
			<notes isHTML="true"></notes>
			<slideThumbnail url="thumb.swf" frame="29"/>
			<slideSpeaker index="1"/>
		</slide>
		<slide id="320" showInTOC="" inSequence="" frameRate="30" totalFrames="30" usePptxSlideDur="0" lockInteractionSlide="false" isHiddenInteractionSl="false" isWrongInteractionSl="false" swfConvertorEngine="Nova" slideDuration="142.93" advance="auto" blockMovement="false" hideplaybar="false" type="normal">
			<transition/>
			<content url="Slide29.swf" id="320"/>
			<backdrop displayBgSp="true"/>
			<master id="2" frameNum="0"/>
			<layout id="2" frameNum="0"/>
			<slidexml><AS3Class className="TL_9b3721efe93d484cabfefd228a544c4dyxy" classType="PptTmline_xyxyxyxyxyxyxyxyxyxyxyxyxyxy" frameRate="30" normalSlide="1"><OnLoadCallBacks/><Audios/></AS3Class></slidexml>
			<clickAnimations></clickAnimations>
			<webObjectContents/>
			<flvContents/>
			<audios id="30" duration=" 142930">
				<media url="a24x30.mp3" startMsecs="0" duration="142930" startAtMSecs="0"/>
			</audios>
			<playbackActions></playbackActions>
			<slideTitle>@@</slideTitle>
			<notes isHTML="true">&lt;TextFlow xmlns = "http://ns.adobe.com/textLayout/2008" fontFamily = "Verdana" fontSize = "9"&gt;&lt;p&gt;&lt;span &gt;plaquettes, endothélium, lipides&lt;/span&gt;&lt;span &gt;&lt;br/&gt;&lt;/span&gt;&lt;span &gt;plasmatiques, fluidité membranaire, fonctions&lt;/span&gt;&lt;span &gt;&lt;br/&gt;&lt;/span&gt;&lt;span &gt;leucocytaires.&lt;/span&gt;&lt;span &gt;&lt;br/&gt;&lt;/span&gt;&lt;/p&gt;&lt;/TextFlow&gt;</notes>
			<slideThumbnail url="thumb.swf" frame="30"/>
			<slideSpeaker index="1"/>
		</slide>
		<slide id="321" showInTOC="" inSequence="" frameRate="30" totalFrames="30" usePptxSlideDur="0" lockInteractionSlide="false" isHiddenInteractionSl="false" isWrongInteractionSl="false" swfConvertorEngine="Nova" slideDuration="109.82" advance="auto" blockMovement="false" hideplaybar="false" type="normal">
			<transition/>
			<content url="Slide30.swf" id="321"/>
			<backdrop displayBgSp="true"/>
			<master id="2" frameNum="0"/>
			<layout id="2" frameNum="0"/>
			<slidexml><AS3Class className="TL_e4ee8afec94b4ed1a807d349e3e3367dyxy" classType="PptTmline_xyxyxyxyxyxyxyxyxyxyxyxyxyxy" frameRate="30" normalSlide="1"><OnLoadCallBacks/><Audios/></AS3Class></slidexml>
			<clickAnimations></clickAnimations>
			<webObjectContents/>
			<flvContents/>
			<audios id="31" duration=" 109820">
				<media url="a24x31.mp3" startMsecs="0" duration="109820" startAtMSecs="0"/>
			</audios>
			<playbackActions></playbackActions>
			<slideTitle>@@</slideTitle>
			<notes isHTML="true">&lt;TextFlow xmlns = "http://ns.adobe.com/textLayout/2008" fontFamily = "Verdana" fontSize = "9"&gt;&lt;p&gt;&lt;span &gt;plaquettes, endothélium, lipides&lt;/span&gt;&lt;span &gt;&lt;br/&gt;&lt;/span&gt;&lt;span &gt;plasmatiques, fluidité membranaire, fonctions&lt;/span&gt;&lt;span &gt;&lt;br/&gt;&lt;/span&gt;&lt;span &gt;leucocytaires.&lt;/span&gt;&lt;span &gt;&lt;br/&gt;&lt;/span&gt;&lt;/p&gt;&lt;/TextFlow&gt;</notes>
			<slideThumbnail url="thumb.swf" frame="31"/>
			<slideSpeaker index="1"/>
		</slide>
		<slide id="322" showInTOC="" inSequence="" frameRate="30" totalFrames="30" usePptxSlideDur="0" lockInteractionSlide="false" isHiddenInteractionSl="false" isWrongInteractionSl="false" swfConvertorEngine="Nova" slideDuration="88.18" advance="auto" blockMovement="false" hideplaybar="false" type="normal">
			<transition/>
			<content url="Slide31.swf" id="322"/>
			<backdrop displayBgSp="true"/>
			<master id="2" frameNum="0"/>
			<layout id="2" frameNum="0"/>
			<slidexml><AS3Class className="TL_72f6e90b56184dcca284e18226aa702ayxy" classType="PptTmline_xyxyxyxyxyxyxyxyxyxyxyxyxyxy" frameRate="30" normalSlide="1"><OnLoadCallBacks/><Audios/></AS3Class></slidexml>
			<clickAnimations>
				<click startTime="130" isStartRelative="false" duration="534"/>
			</clickAnimations>
			<webObjectContents/>
			<flvContents/>
			<audios id="32" duration=" 88180">
				<media url="a24x32.mp3" startMsecs="0" duration="88180" startAtMSecs="0"/>
			</audios>
			<playbackActions></playbackActions>
			<slideTitle>@@</slideTitle>
			<notes isHTML="true">&lt;TextFlow xmlns = "http://ns.adobe.com/textLayout/2008" fontFamily = "Verdana" fontSize = "9"&gt;&lt;p&gt;&lt;span &gt;plaquettes, endothélium, lipides&lt;/span&gt;&lt;span &gt;&lt;br/&gt;&lt;/span&gt;&lt;span &gt;plasmatiques, fluidité membranaire, fonctions&lt;/span&gt;&lt;span &gt;&lt;br/&gt;&lt;/span&gt;&lt;span &gt;leucocytaires.&lt;/span&gt;&lt;span &gt;&lt;br/&gt;&lt;/span&gt;&lt;/p&gt;&lt;/TextFlow&gt;</notes>
			<slideThumbnail url="thumb.swf" frame="32"/>
			<slideSpeaker index="1"/>
		</slide>
		<slide id="323" showInTOC="" inSequence="" frameRate="30" totalFrames="30" usePptxSlideDur="0" lockInteractionSlide="false" isHiddenInteractionSl="false" isWrongInteractionSl="false" swfConvertorEngine="Nova" slideDuration="77.93" advance="auto" blockMovement="false" hideplaybar="false" type="normal">
			<transition/>
			<content url="Slide32.swf" id="323"/>
			<backdrop displayBgSp="true"/>
			<master id="2" frameNum="0"/>
			<layout id="3" frameNum="0"/>
			<slidexml><AS3Class className="TL_529962dfce5040838413f7f67e7593f7yxy" classType="PptTmline_xyxyxyxyxyxyxyxyxyxyxyxyxyxy" frameRate="30" normalSlide="1"><OnLoadCallBacks/><Audios/></AS3Class></slidexml>
			<clickAnimations></clickAnimations>
			<webObjectContents/>
			<flvContents/>
			<audios id="33" duration=" 77930">
				<media url="a24x33.mp3" startMsecs="0" duration="77930" startAtMSecs="0"/>
			</audios>
			<playbackActions></playbackActions>
			<slideTitle>@Conclusions Théories du Vieillissement  @</slideTitle>
			<notes isHTML="true"></notes>
			<slideThumbnail url="thumb.swf" frame="33"/>
			<slideSpeaker index="1"/>
		</slide>
		<slide id="324" showInTOC="" inSequence="" frameRate="30" totalFrames="30" usePptxSlideDur="0" lockInteractionSlide="false" isHiddenInteractionSl="false" isWrongInteractionSl="false" swfConvertorEngine="Nova" slideDuration="39.87" advance="auto" blockMovement="false" hideplaybar="false" type="normal">
			<transition/>
			<content url="Slide33.swf" id="324"/>
			<backdrop displayBgSp="true"/>
			<master id="2" frameNum="0"/>
			<layout id="2" frameNum="0"/>
			<slidexml><AS3Class className="TL_4821473577614b0490971651d5cbad89yxy" classType="PptTmline_xyxyxyxyxyxyxyxyxyxyxyxyxyxy" frameRate="30" normalSlide="1"><OnLoadCallBacks/><Audios/></AS3Class></slidexml>
			<clickAnimations></clickAnimations>
			<webObjectContents/>
			<flvContents/>
			<audios id="34" duration=" 39870">
				<media url="a24x34.mp3" startMsecs="0" duration="39870" startAtMSecs="0"/>
			</audios>
			<playbackActions></playbackActions>
			<slideTitle>@@</slideTitle>
			<notes isHTML="true"></notes>
			<slideThumbnail url="thumb.swf" frame="34"/>
			<slideSpeaker index="1"/>
		</slide>
		<slide id="325" showInTOC="" inSequence="" frameRate="30" totalFrames="30" usePptxSlideDur="0" lockInteractionSlide="false" isHiddenInteractionSl="false" isWrongInteractionSl="false" swfConvertorEngine="Nova" slideDuration="5" advance="auto" blockMovement="false" hideplaybar="false" type="normal">
			<transition/>
			<content url="Slide34.swf" id="325"/>
			<backdrop displayBgSp="true"/>
			<master id="2" frameNum="0"/>
			<layout id="4" frameNum="0"/>
			<slidexml><AS3Class className="TL_2cbd225294b1474b8795be4bacf09eb6yxy" classType="PptTmline_xyxyxyxyxyxyxyxyxyxyxyxyxyxy" frameRate="30" normalSlide="1"><OnLoadCallBacks/><Audios/></AS3Class></slidexml>
			<clickAnimations></clickAnimations>
			<webObjectContents/>
			<flvContents/>
			<audios duration="5000"/>
			<playbackActions></playbackActions>
			<slideTitle>@@</slideTitle>
			<notes isHTML="true"></notes>
			<slideThumbnail url="thumb.swf" frame="35"/>
			<slideSpeaker index="1"/>
		</slide>
		<slide id="290" showInTOC="" inSequence="" frameRate="30" totalFrames="30" usePptxSlideDur="0" lockInteractionSlide="false" isHiddenInteractionSl="false" isWrongInteractionSl="false" swfConvertorEngine="Nova" slideDuration="4.59" advance="auto" blockMovement="false" hideplaybar="false" type="normal">
			<transition/>
			<content url="Slide35.swf" id="290"/>
			<backdrop displayBgSp="true"/>
			<master id="1" frameNum="0"/>
			<layout id="5" frameNum="0"/>
			<slidexml><AS3Class className="TL_cbb73b62616d44a39b810f5a5d7706eeyxy" classType="PptTmline_xyxyxyxyxyxyxyxyxyxyxyxyxyxy" frameRate="30" normalSlide="1"><OnLoadCallBacks/><Audios/></AS3Class></slidexml>
			<clickAnimations></clickAnimations>
			<webObjectContents/>
			<flvContents/>
			<audios duration="4590"/>
			<playbackActions></playbackActions>
			<slideTitle>@Mentions légales@</slideTitle>
			<notes isHTML="true"></notes>
			<slideThumbnail url="thumb.swf" frame="36"/>
			<slideSpeaker index="1"/>
		</slide>
	</slides>
	<quizzes>
		<reportingOptions statusReportingOption="0" successReportingCriteria="-1" completionReportingCriteria="-1" slideViewCompletionCriteria="-1" slideViewSuccessCriteria="-1" quizCompletionCriteria="-1" quizSuccessCriteria="-1" completionCriteriaSlideViewVal="0" successCriteriaSlideViewVal="0" dataToReport="1" exitNormal="0" isTracked="false"></reportingOptions>
		<quizSettings showQuestionList="false" showScores="true" showPassScore="false" showCurrentScore="false" showQuestionMarks="false" showAttempts="true" showQuizAttempts="false" showQuestionAttempts="false" showQuestionCorrectFeedback="true" showQuestionIncorrectFeedback="true" showQuizNavigationWarning="false"></quizSettings>
	</quizzes>
	<attachments></attachments>
</presentation>
